{
    "Q49": {
        "ab": {
            "Title": "\u0410\u04a9\u0430\u0434\u0430\u0442\u04d9\u0438 \u0410\u043c\u0435\u0440\u0438\u043a\u0430",
            "Link": "https://ab.wikipedia.org/wiki/%D0%90%D2%A9%D0%B0%D0%B4%D0%B0%D1%82%D3%99%D0%B8_%D0%90%D0%BC%D0%B5%D1%80%D0%B8%D0%BA%D0%B0"
        },
        "ace": {
            "Title": "Amirika Utara",
            "Link": "https://ace.wikipedia.org/wiki/Amirika_Utara"
        },
        "ady": {
            "Title": "\u0418\u0448\u044a\u0445\u044a\u044d\u0440\u044d \u0410\u043c\u0435\u0440\u0438\u043a\u044d",
            "Link": "https://ady.wikipedia.org/wiki/%D0%98%D1%88%D1%8A%D1%85%D1%8A%D1%8D%D1%80%D1%8D_%D0%90%D0%BC%D0%B5%D1%80%D0%B8%D0%BA%D1%8D"
        },
        "af": {
            "Title": "Noord-Amerika",
            "Link": "https://af.wikipedia.org/wiki/Noord-Amerika"
        },
        "gsw": {
            "Title": "Nordamerika",
            "Link": "https://als.wikipedia.org/wiki/Nordamerika"
        },
        "am": {
            "Title": "\u1235\u121c\u1295 \u12a0\u121c\u122a\u12ab",
            "Link": "https://am.wikipedia.org/wiki/%E1%88%B5%E1%88%9C%E1%8A%95_%E1%8A%A0%E1%88%9C%E1%88%AA%E1%8A%AB"
        },
        "ang": {
            "Title": "Nor\u00f0america",
            "Link": "https://ang.wikipedia.org/wiki/Nor%C3%B0america"
        },
        "ann": {
            "Title": "Amerika Iny\u1ecdn\u0304",
            "Link": "https://ann.wikipedia.org/wiki/Amerika_Iny%E1%BB%8Dn%CC%84"
        },
        "anp": {
            "Title": "\u0909\u0924\u094d\u0924\u0930\u0940 \u0905\u092e\u0930\u093f\u0915\u093e",
            "Link": "https://anp.wikipedia.org/wiki/%E0%A4%89%E0%A4%A4%E0%A5%8D%E0%A4%A4%E0%A4%B0%E0%A5%80_%E0%A4%85%E0%A4%AE%E0%A4%B0%E0%A4%BF%E0%A4%95%E0%A4%BE"
        },
        "an": {
            "Title": "America d'o Norte",
            "Link": "https://an.wikipedia.org/wiki/America_d%27o_Norte"
        },
        "arc": {
            "Title": "\u0710\u0721\u072a\u071d\u0729\u0710 \u0713\u072a\u0712\u071d\u071d\u072c\u0710",
            "Link": "https://arc.wikipedia.org/wiki/%DC%90%DC%A1%DC%AA%DC%9D%DC%A9%DC%90_%DC%93%DC%AA%DC%92%DC%9D%DC%9D%DC%AC%DC%90"
        },
        "ar": {
            "Title": "\u062a\u0635\u0646\u064a\u0641:\u0623\u0645\u0631\u064a\u0643\u0627 \u0627\u0644\u0634\u0645\u0627\u0644\u064a\u0629",
            "Link": "https://ar.wikinews.org/wiki/%D8%AA%D8%B5%D9%86%D9%8A%D9%81:%D8%A3%D9%85%D8%B1%D9%8A%D9%83%D8%A7_%D8%A7%D9%84%D8%B4%D9%85%D8%A7%D9%84%D9%8A%D8%A9"
        },
        "ary": {
            "Title": "\u0623\u0645\u0631\u064a\u0643\u0627 \u0627\u0644\u0634\u0645\u0627\u0644\u064a\u0629",
            "Link": "https://ary.wikipedia.org/wiki/%D8%A3%D9%85%D8%B1%D9%8A%D9%83%D8%A7_%D8%A7%D9%84%D8%B4%D9%85%D8%A7%D9%84%D9%8A%D8%A9"
        },
        "arz": {
            "Title": "\u0627\u0645\u0631\u064a\u0643\u0627 \u0627\u0644\u0634\u0645\u0627\u0644\u064a\u0647",
            "Link": "https://arz.wikipedia.org/wiki/%D8%A7%D9%85%D8%B1%D9%8A%D9%83%D8%A7_%D8%A7%D9%84%D8%B4%D9%85%D8%A7%D9%84%D9%8A%D9%87"
        },
        "ast": {
            "Title": "Am\u00e9rica del Norte",
            "Link": "https://ast.wikipedia.org/wiki/Am%C3%A9rica_del_Norte"
        },
        "as": {
            "Title": "\u0989\u09a4\u09cd\u09a4\u09f0 \u0986\u09ae\u09c7\u09f0\u09bf\u0995\u09be",
            "Link": "https://as.wikipedia.org/wiki/%E0%A6%89%E0%A6%A4%E0%A7%8D%E0%A6%A4%E0%A7%B0_%E0%A6%86%E0%A6%AE%E0%A7%87%E0%A7%B0%E0%A6%BF%E0%A6%95%E0%A6%BE"
        },
        "avk": {
            "Title": "Lentefa Amerika",
            "Link": "https://avk.wikipedia.org/wiki/Lentefa_Amerika"
        },
        "awa": {
            "Title": "\u0909\u0924\u094d\u0924\u0930 \u0905\u092e\u0947\u0930\u093f\u0915\u093e",
            "Link": "https://awa.wikipedia.org/wiki/%E0%A4%89%E0%A4%A4%E0%A5%8D%E0%A4%A4%E0%A4%B0_%E0%A4%85%E0%A4%AE%E0%A5%87%E0%A4%B0%E0%A4%BF%E0%A4%95%E0%A4%BE"
        },
        "azb": {
            "Title": "\u0634\u0648\u0645\u0627\u0644\u06cc \u0622\u0645\u0631\u06cc\u06a9\u0627",
            "Link": "https://azb.wikipedia.org/wiki/%D8%B4%D9%88%D9%85%D8%A7%D9%84%DB%8C_%D8%A2%D9%85%D8%B1%DB%8C%DA%A9%D8%A7"
        },
        "az": {
            "Title": "\u015eimali Amerika",
            "Link": "https://az.wikiquote.org/wiki/%C5%9Eimali_Amerika"
        },
        "ban": {
            "Title": "Am\u00e9rika Kal\u00e9r",
            "Link": "https://ban.wikipedia.org/wiki/Am%C3%A9rika_Kal%C3%A9r"
        },
        "bar": {
            "Title": "Noadamerika",
            "Link": "https://bar.wikipedia.org/wiki/Noadamerika"
        },
        "sgs": {
            "Title": "\u0160iaur\u0117s Amer\u0117ka",
            "Link": "https://bat-smg.wikipedia.org/wiki/%C5%A0iaur%C4%97s_Amer%C4%97ka"
        },
        "ba": {
            "Title": "\u0422\u04e9\u043d\u044c\u044f\u04a1 \u0410\u043c\u0435\u0440\u0438\u043a\u0430",
            "Link": "https://ba.wikipedia.org/wiki/%D0%A2%D3%A9%D0%BD%D1%8C%D1%8F%D2%A1_%D0%90%D0%BC%D0%B5%D1%80%D0%B8%D0%BA%D0%B0"
        },
        "bcl": {
            "Title": "Amihanan na Amerika",
            "Link": "https://bcl.wikipedia.org/wiki/Amihanan_na_Amerika"
        },
        "be-tarask": {
            "Title": "\u041f\u0430\u045e\u043d\u043e\u0447\u043d\u0430\u044f \u0410\u043c\u044d\u0440\u044b\u043a\u0430",
            "Link": "https://be-tarask.wikipedia.org/wiki/%D0%9F%D0%B0%D1%9E%D0%BD%D0%BE%D1%87%D0%BD%D0%B0%D1%8F_%D0%90%D0%BC%D1%8D%D1%80%D1%8B%D0%BA%D0%B0"
        },
        "be": {
            "Title": "\u041f\u0430\u045e\u043d\u043e\u0447\u043d\u0430\u044f \u0410\u043c\u0435\u0440\u044b\u043a\u0430",
            "Link": "https://be.wikipedia.org/wiki/%D0%9F%D0%B0%D1%9E%D0%BD%D0%BE%D1%87%D0%BD%D0%B0%D1%8F_%D0%90%D0%BC%D0%B5%D1%80%D1%8B%D0%BA%D0%B0"
        },
        "bg": {
            "Title": "\u041a\u0430\u0442\u0435\u0433\u043e\u0440\u0438\u044f:\u0421\u0435\u0432\u0435\u0440\u043d\u0430 \u0410\u043c\u0435\u0440\u0438\u043a\u0430",
            "Link": "https://bg.wikinews.org/wiki/%D0%9A%D0%B0%D1%82%D0%B5%D0%B3%D0%BE%D1%80%D0%B8%D1%8F:%D0%A1%D0%B5%D0%B2%D0%B5%D1%80%D0%BD%D0%B0_%D0%90%D0%BC%D0%B5%D1%80%D0%B8%D0%BA%D0%B0"
        },
        "bh": {
            "Title": "\u0909\u0924\u094d\u0924\u0930 \u0905\u092e\u0947\u0930\u093f\u0915\u093e",
            "Link": "https://bh.wikipedia.org/wiki/%E0%A4%89%E0%A4%A4%E0%A5%8D%E0%A4%A4%E0%A4%B0_%E0%A4%85%E0%A4%AE%E0%A5%87%E0%A4%B0%E0%A4%BF%E0%A4%95%E0%A4%BE"
        },
        "bi": {
            "Title": "Not Amerika",
            "Link": "https://bi.wikipedia.org/wiki/Not_Amerika"
        },
        "bjn": {
            "Title": "Amirika Utara",
            "Link": "https://bjn.wikipedia.org/wiki/Amirika_Utara"
        },
        "blk": {
            "Title": "\u1021\u1019\u1031\u108f\u101b\u102d\u1000\u1011\u1004\u103a\uaa7b",
            "Link": "https://blk.wikipedia.org/wiki/%E1%80%A1%E1%80%99%E1%80%B1%E1%82%8F%E1%80%9B%E1%80%AD%E1%80%80%E1%80%91%E1%80%84%E1%80%BA%EA%A9%BB"
        },
        "bm": {
            "Title": "Saheli Amerika",
            "Link": "https://bm.wikipedia.org/wiki/Saheli_Amerika"
        },
        "bn": {
            "Title": "\u0989\u09a4\u09cd\u09a4\u09b0 \u0986\u09ae\u09c7\u09b0\u09bf\u0995\u09be",
            "Link": "https://bn.wikivoyage.org/wiki/%E0%A6%89%E0%A6%A4%E0%A7%8D%E0%A6%A4%E0%A6%B0_%E0%A6%86%E0%A6%AE%E0%A7%87%E0%A6%B0%E0%A6%BF%E0%A6%95%E0%A6%BE"
        },
        "bo": {
            "Title": "\u0f42\u0fb3\u0f72\u0f44\u0f0b\u0f46\u0f7a\u0f53\u0f0b\u0f68\u0f0b\u0f58\u0f7a\u0f0b\u0f62\u0f72\u0f0b\u0f41\u0f0b\u0f56\u0fb1\u0f44\u0f0b\u0f58\u0f0d",
            "Link": "https://bo.wikipedia.org/wiki/%E0%BD%82%E0%BE%B3%E0%BD%B2%E0%BD%84%E0%BC%8B%E0%BD%86%E0%BD%BA%E0%BD%93%E0%BC%8B%E0%BD%A8%E0%BC%8B%E0%BD%98%E0%BD%BA%E0%BC%8B%E0%BD%A2%E0%BD%B2%E0%BC%8B%E0%BD%81%E0%BC%8B%E0%BD%96%E0%BE%B1%E0%BD%84%E0%BC%8B%E0%BD%98%E0%BC%8D"
        },
        "br": {
            "Title": "Norzhamerika",
            "Link": "https://br.wikipedia.org/wiki/Norzhamerika"
        },
        "bs": {
            "Title": "Kategorija:Sjeverna Amerika",
            "Link": "https://bs.wikinews.org/wiki/Kategorija:Sjeverna_Amerika"
        },
        "btm": {
            "Title": "Amerika Utara",
            "Link": "https://btm.wikipedia.org/wiki/Amerika_Utara"
        },
        "bxr": {
            "Title": "\u0425\u043e\u0439\u0442\u043e \u0410\u043c\u0435\u0440\u0438\u043a\u044d",
            "Link": "https://bxr.wikipedia.org/wiki/%D0%A5%D0%BE%D0%B9%D1%82%D0%BE_%D0%90%D0%BC%D0%B5%D1%80%D0%B8%D0%BA%D1%8D"
        },
        "ca": {
            "Title": "Am\u00e8rica del Nord",
            "Link": "https://ca.wikipedia.org/wiki/Am%C3%A8rica_del_Nord"
        },
        "cdo": {
            "Title": "B\u00e1e\u0324k M\u012b-ci\u016d",
            "Link": "https://cdo.wikipedia.org/wiki/B%C3%A1e%CC%A4k_M%C4%AB-ci%C5%AD"
        },
        "ceb": {
            "Title": "Amihanang Amerika",
            "Link": "https://ceb.wikipedia.org/wiki/Amihanang_Amerika"
        },
        "ce": {
            "Title": "\u041a\u044a\u0438\u043b\u0431\u0430\u0441\u0435\u0434\u0430 \u0410\u043c\u0435\u0440\u0438\u043a\u0430",
            "Link": "https://ce.wikipedia.org/wiki/%D0%9A%D1%8A%D0%B8%D0%BB%D0%B1%D0%B0%D1%81%D0%B5%D0%B4%D0%B0_%D0%90%D0%BC%D0%B5%D1%80%D0%B8%D0%BA%D0%B0"
        },
        "chr": {
            "Title": "\u13e7\u13f4\u13e2 \u13a0\u13b9\u13f0\u13df",
            "Link": "https://chr.wikipedia.org/wiki/%E1%8F%A7%E1%8F%B4%E1%8F%A2_%E1%8E%A0%E1%8E%B9%E1%8F%B0%E1%8F%9F"
        },
        "ckb": {
            "Title": "\u0626\u06d5\u0645\u0631\u06cc\u06a9\u0627\u06cc \u0628\u0627\u06a9\u0648\u0648\u0631",
            "Link": "https://ckb.wikipedia.org/wiki/%D8%A6%DB%95%D9%85%D8%B1%DB%8C%DA%A9%D8%A7%DB%8C_%D8%A8%D8%A7%DA%A9%D9%88%D9%88%D8%B1"
        },
        "co": {
            "Title": "America settentriunale",
            "Link": "https://co.wikipedia.org/wiki/America_settentriunale"
        },
        "crh": {
            "Title": "\u015eimaliy Amerika",
            "Link": "https://crh.wikipedia.org/wiki/%C5%9Eimaliy_Amerika"
        },
        "csb": {
            "Title": "Nordow\u00f4 Amerika",
            "Link": "https://csb.wikipedia.org/wiki/Nordow%C3%B4_Amerika"
        },
        "cs": {
            "Title": "Severn\u00ed Amerika",
            "Link": "https://cs.wikivoyage.org/wiki/Severn%C3%AD_Amerika"
        },
        "cu": {
            "Title": "\u0421\u0463\u0432\u0454\u0440\u044c\u043d\u0430 \u0410\u043c\u0454\u0440\u0457\u043a\u0430",
            "Link": "https://cu.wikipedia.org/wiki/%D0%A1%D1%A3%D0%B2%D1%94%D1%80%D1%8C%D0%BD%D0%B0_%D0%90%D0%BC%D1%94%D1%80%D1%97%D0%BA%D0%B0"
        },
        "cv": {
            "Title": "\u00c7\u0443\u0440\u00e7\u0115\u0440 \u0410\u043c\u0435\u0440\u0438\u043a\u0430",
            "Link": "https://cv.wikipedia.org/wiki/%C3%87%D1%83%D1%80%C3%A7%C4%95%D1%80_%D0%90%D0%BC%D0%B5%D1%80%D0%B8%D0%BA%D0%B0"
        },
        "cy": {
            "Title": "Gogledd America",
            "Link": "https://cy.wikipedia.org/wiki/Gogledd_America"
        },
        "da": {
            "Title": "Nordamerika",
            "Link": "https://da.wikipedia.org/wiki/Nordamerika"
        },
        "de": {
            "Title": "Nordamerika",
            "Link": "https://de.wikivoyage.org/wiki/Nordamerika"
        },
        "diq": {
            "Title": "Amerikay Z\u0131mey",
            "Link": "https://diq.wikipedia.org/wiki/Amerikay_Z%C4%B1mey"
        },
        "dsb": {
            "Title": "P\u00f3dpo\u0142nocna Amerika",
            "Link": "https://dsb.wikipedia.org/wiki/P%C3%B3dpo%C5%82nocna_Amerika"
        },
        "dtp": {
            "Title": "Amirika Koibutan",
            "Link": "https://dtp.wikipedia.org/wiki/Amirika_Koibutan"
        },
        "dty": {
            "Title": "\u0909\u0924\u094d\u0924\u0930 \u0905\u092e\u0947\u0930\u093f\u0915\u093e",
            "Link": "https://dty.wikipedia.org/wiki/%E0%A4%89%E0%A4%A4%E0%A5%8D%E0%A4%A4%E0%A4%B0_%E0%A4%85%E0%A4%AE%E0%A5%87%E0%A4%B0%E0%A4%BF%E0%A4%95%E0%A4%BE"
        },
        "el": {
            "Title": "\u0392\u03cc\u03c1\u03b5\u03b9\u03b1 \u0391\u03bc\u03b5\u03c1\u03b9\u03ba\u03ae",
            "Link": "https://el.wikivoyage.org/wiki/%CE%92%CF%8C%CF%81%CE%B5%CE%B9%CE%B1_%CE%91%CE%BC%CE%B5%CF%81%CE%B9%CE%BA%CE%AE"
        },
        "en": {
            "Title": "North America",
            "Link": "https://commons.wikimedia.org/wiki/North_America"
        },
        "eo": {
            "Title": "Nordameriko",
            "Link": "https://eo.wikivoyage.org/wiki/Nordameriko"
        },
        "es": {
            "Title": "Am\u00e9rica del Norte",
            "Link": "https://es.wikipedia.org/wiki/Am%C3%A9rica_del_Norte"
        },
        "et": {
            "Title": "P\u00f5hja-Ameerika manner",
            "Link": "https://et.wikipedia.org/wiki/P%C3%B5hja-Ameerika_manner"
        },
        "eu": {
            "Title": "Ipar Amerika",
            "Link": "https://eu.wikipedia.org/wiki/Ipar_Amerika"
        },
        "ext": {
            "Title": "Am\u00e9rica el Norti",
            "Link": "https://ext.wikipedia.org/wiki/Am%C3%A9rica_el_Norti"
        },
        "fa": {
            "Title": "\u0622\u0645\u0631\u06cc\u06a9\u0627\u06cc \u0634\u0645\u0627\u0644\u06cc",
            "Link": "https://fa.wikivoyage.org/wiki/%D8%A2%D9%85%D8%B1%DB%8C%DA%A9%D8%A7%DB%8C_%D8%B4%D9%85%D8%A7%D9%84%DB%8C"
        },
        "vro": {
            "Title": "P\u00f5h'a-Ameeriga",
            "Link": "https://fiu-vro.wikipedia.org/wiki/P%C3%B5h%27a-Ameeriga"
        },
        "fi": {
            "Title": "Pohjois-Amerikka",
            "Link": "https://fi.wikivoyage.org/wiki/Pohjois-Amerikka"
        },
        "fj": {
            "Title": "Vualiku Amerika",
            "Link": "https://fj.wikipedia.org/wiki/Vualiku_Amerika"
        },
        "fo": {
            "Title": "Nor\u00f0uramerika",
            "Link": "https://fo.wikipedia.org/wiki/Nor%C3%B0uramerika"
        },
        "frp": {
            "Title": "Am\u00e8rica de Bise",
            "Link": "https://frp.wikipedia.org/wiki/Am%C3%A8rica_de_Bise"
        },
        "frr": {
            "Title": "Nuurd-Ameerikoo",
            "Link": "https://frr.wikipedia.org/wiki/Nuurd-Ameerikoo"
        },
        "fr": {
            "Title": "Am\u00e9rique du Nord",
            "Link": "https://fr.wikivoyage.org/wiki/Am%C3%A9rique_du_Nord"
        },
        "fur": {
            "Title": "Americhe dal Nord",
            "Link": "https://fur.wikipedia.org/wiki/Americhe_dal_Nord"
        },
        "fy": {
            "Title": "Noard-Amearika",
            "Link": "https://fy.wikipedia.org/wiki/Noard-Amearika"
        },
        "gag": {
            "Title": "Poyraz Amerika",
            "Link": "https://gag.wikipedia.org/wiki/Poyraz_Amerika"
        },
        "gan": {
            "Title": "\u5317\u7f8e\u6d32",
            "Link": "https://gan.wikipedia.org/wiki/%E5%8C%97%E7%BE%8E%E6%B4%B2"
        },
        "ga": {
            "Title": "Meirice\u00e1 Thuaidh",
            "Link": "https://ga.wikipedia.org/wiki/Meirice%C3%A1_Thuaidh"
        },
        "gcr": {
            "Title": "Lanm\u00e9rik di N\u00f2",
            "Link": "https://gcr.wikipedia.org/wiki/Lanm%C3%A9rik_di_N%C3%B2"
        },
        "gd": {
            "Title": "Aimearaga a Tuath",
            "Link": "https://gd.wikipedia.org/wiki/Aimearaga_a_Tuath"
        },
        "glk": {
            "Title": "\u06a9\u0644\u0633\u064a\u0627\u064a\u064a \u0622\u0645\u0631\u064a\u06a9\u0627",
            "Link": "https://glk.wikipedia.org/wiki/%DA%A9%D9%84%D8%B3%D9%8A%D8%A7%D9%8A%D9%8A_%D8%A2%D9%85%D8%B1%D9%8A%DA%A9%D8%A7"
        },
        "gl": {
            "Title": "Am\u00e9rica do Norte",
            "Link": "https://gl.wikipedia.org/wiki/Am%C3%A9rica_do_Norte"
        },
        "gn": {
            "Title": "Yvate Am\u00e9rika",
            "Link": "https://gn.wikipedia.org/wiki/Yvate_Am%C3%A9rika"
        },
        "got": {
            "Title": "\ud800\udf3d\ud800\udf30\ud800\udf3f\ud800\udf42\ud800\udf38\ud800\udf30 \ud800\udf30\ud800\udf3c\ud800\udf34\ud800\udf42\ud800\udf39\ud800\udf3a\ud800\udf30",
            "Link": "https://got.wikipedia.org/wiki/%F0%90%8C%BD%F0%90%8C%B0%F0%90%8C%BF%F0%90%8D%82%F0%90%8C%B8%F0%90%8C%B0_%F0%90%8C%B0%F0%90%8C%BC%F0%90%8C%B4%F0%90%8D%82%F0%90%8C%B9%F0%90%8C%BA%F0%90%8C%B0"
        },
        "gpe": {
            "Title": "North America",
            "Link": "https://gpe.wikipedia.org/wiki/North_America"
        },
        "gu": {
            "Title": "\u0a89\u0aa4\u0acd\u0aa4\u0ab0 \u0a85\u0aae\u0ac7\u0ab0\u0abf\u0a95\u0abe",
            "Link": "https://gu.wikipedia.org/wiki/%E0%AA%89%E0%AA%A4%E0%AB%8D%E0%AA%A4%E0%AA%B0_%E0%AA%85%E0%AA%AE%E0%AB%87%E0%AA%B0%E0%AA%BF%E0%AA%95%E0%AA%BE"
        },
        "gv": {
            "Title": "America Hwoaie",
            "Link": "https://gv.wikipedia.org/wiki/America_Hwoaie"
        },
        "hak": {
            "Title": "Pet M\u00ee-ch\u00fb",
            "Link": "https://hak.wikipedia.org/wiki/Pet_M%C3%AE-ch%C3%BB"
        },
        "ha": {
            "Title": "Amurka ta Arewa",
            "Link": "https://ha.wikipedia.org/wiki/Amurka_ta_Arewa"
        },
        "haw": {
            "Title": "\u02bbAmelika \u02bb\u0100kau",
            "Link": "https://haw.wikipedia.org/wiki/%CA%BBAmelika_%CA%BB%C4%80kau"
        },
        "he": {
            "Title": "\u05d0\u05de\u05e8\u05d9\u05e7\u05d4 \u05d4\u05e6\u05e4\u05d5\u05e0\u05d9\u05ea",
            "Link": "https://he.wikivoyage.org/wiki/%D7%90%D7%9E%D7%A8%D7%99%D7%A7%D7%94_%D7%94%D7%A6%D7%A4%D7%95%D7%A0%D7%99%D7%AA"
        },
        "hif": {
            "Title": "North America",
            "Link": "https://hif.wikipedia.org/wiki/North_America"
        },
        "hi": {
            "Title": "\u0909\u0924\u094d\u0924\u0930 \u0905\u092e\u0947\u0930\u093f\u0915\u093e",
            "Link": "https://hi.wikipedia.org/wiki/%E0%A4%89%E0%A4%A4%E0%A5%8D%E0%A4%A4%E0%A4%B0_%E0%A4%85%E0%A4%AE%E0%A5%87%E0%A4%B0%E0%A4%BF%E0%A4%95%E0%A4%BE"
        },
        "hr": {
            "Title": "Sjeverna Amerika",
            "Link": "https://hr.wikipedia.org/wiki/Sjeverna_Amerika"
        },
        "hsb": {
            "Title": "Sewjerna Amerika",
            "Link": "https://hsb.wikipedia.org/wiki/Sewjerna_Amerika"
        },
        "ht": {
            "Title": "Amerik din\u00f2",
            "Link": "https://ht.wikipedia.org/wiki/Amerik_din%C3%B2"
        },
        "hu": {
            "Title": "\u00c9szak-Amerika",
            "Link": "https://hu.wikipedia.org/wiki/%C3%89szak-Amerika"
        },
        "hy": {
            "Title": "\u0540\u0575\u0578\u0582\u057d\u056b\u057d\u0561\u0575\u056b\u0576 \u0531\u0574\u0565\u0580\u056b\u056f\u0561",
            "Link": "https://hy.wikipedia.org/wiki/%D5%80%D5%B5%D5%B8%D6%82%D5%BD%D5%AB%D5%BD%D5%A1%D5%B5%D5%AB%D5%B6_%D4%B1%D5%B4%D5%A5%D6%80%D5%AB%D5%AF%D5%A1"
        },
        "ia": {
            "Title": "America del Nord",
            "Link": "https://ia.wikipedia.org/wiki/America_del_Nord"
        },
        "iba": {
            "Title": "Amerika Utara",
            "Link": "https://iba.wikipedia.org/wiki/Amerika_Utara"
        },
        "id": {
            "Title": "Amerika Utara",
            "Link": "https://id.wikipedia.org/wiki/Amerika_Utara"
        },
        "ie": {
            "Title": "America del Nord",
            "Link": "https://ie.wikipedia.org/wiki/America_del_Nord"
        },
        "ig": {
            "Title": "Olile anyanwu Amerika",
            "Link": "https://ig.wikipedia.org/wiki/Olile_anyanwu_Amerika"
        },
        "ik": {
            "Title": "Salli\u00f1iq Amirika",
            "Link": "https://ik.wikipedia.org/wiki/Salli%C3%B1iq_Amirika"
        },
        "ilo": {
            "Title": "Amianan nga Amerika",
            "Link": "https://ilo.wikipedia.org/wiki/Amianan_nga_Amerika"
        },
        "inh": {
            "Title": "\u0413\u04c0\u0438\u043d\u0431\u0443\u0445\u0435\u0440\u0430 \u0410\u043c\u0435\u0440\u0438\u043a\u0430",
            "Link": "https://inh.wikipedia.org/wiki/%D0%93%D3%80%D0%B8%D0%BD%D0%B1%D1%83%D1%85%D0%B5%D1%80%D0%B0_%D0%90%D0%BC%D0%B5%D1%80%D0%B8%D0%BA%D0%B0"
        },
        "is": {
            "Title": "Nor\u00f0ur-Amer\u00edka",
            "Link": "https://is.wikipedia.org/wiki/Nor%C3%B0ur-Amer%C3%ADka"
        },
        "it": {
            "Title": "America del Nord",
            "Link": "https://it.wikivoyage.org/wiki/America_del_Nord"
        },
        "iu": {
            "Title": "\u140a\u14a5\u140a\u1546\u1472 \u1450\u14c4\u1555\u140a\u1585",
            "Link": "https://iu.wikipedia.org/wiki/%E1%90%8A%E1%92%A5%E1%90%8A%E1%95%86%E1%91%B2_%E1%91%90%E1%93%84%E1%95%95%E1%90%8A%E1%96%85"
        },
        "jam": {
            "Title": "Naat Amoerka",
            "Link": "https://jam.wikipedia.org/wiki/Naat_Amoerka"
        },
        "ja": {
            "Title": "\u5317\u30a2\u30e1\u30ea\u30ab",
            "Link": "https://ja.wikivoyage.org/wiki/%E5%8C%97%E3%82%A2%E3%83%A1%E3%83%AA%E3%82%AB"
        },
        "jbo": {
            "Title": "bemtu'a",
            "Link": "https://jbo.wikipedia.org/wiki/bemtu%27a"
        },
        "jv": {
            "Title": "Am\u00e9rika Lor",
            "Link": "https://jv.wikipedia.org/wiki/Am%C3%A9rika_Lor"
        },
        "kaa": {
            "Title": "Arqa Amerika",
            "Link": "https://kaa.wikipedia.org/wiki/Arqa_Amerika"
        },
        "kab": {
            "Title": "Tamrikt n Ugafa",
            "Link": "https://kab.wikipedia.org/wiki/Tamrikt_n_Ugafa"
        },
        "ka": {
            "Title": "\u10e9\u10e0\u10d3\u10d8\u10da\u10dd\u10d4\u10d7\u10d8 \u10d0\u10db\u10d4\u10e0\u10d8\u10d9\u10d0",
            "Link": "https://ka.wikipedia.org/wiki/%E1%83%A9%E1%83%A0%E1%83%93%E1%83%98%E1%83%9A%E1%83%9D%E1%83%94%E1%83%97%E1%83%98_%E1%83%90%E1%83%9B%E1%83%94%E1%83%A0%E1%83%98%E1%83%99%E1%83%90"
        },
        "kbd": {
            "Title": "\u0418\u0448\u0445\u044a\u044d\u0440\u044d \u0410\u043c\u0435\u0440\u0438\u043a\u044d",
            "Link": "https://kbd.wikipedia.org/wiki/%D0%98%D1%88%D1%85%D1%8A%D1%8D%D1%80%D1%8D_%D0%90%D0%BC%D0%B5%D1%80%D0%B8%D0%BA%D1%8D"
        },
        "kbp": {
            "Title": "Amerika n\u025b hayi t\u025bt\u028b wandamm",
            "Link": "https://kbp.wikipedia.org/wiki/Amerika_n%C9%9B_hayi_t%C9%9Bt%CA%8B_wandamm"
        },
        "kcg": {
            "Title": "Amerika A\u0331za",
            "Link": "https://kcg.wikipedia.org/wiki/Amerika_A%CC%B1za"
        },
        "kge": {
            "Title": "Amerika Liba",
            "Link": "https://kge.wikipedia.org/wiki/Amerika_Liba"
        },
        "kg": {
            "Title": "Amelika ya Nodi",
            "Link": "https://kg.wikipedia.org/wiki/Amelika_ya_Nodi"
        },
        "kk": {
            "Title": "\u0421\u043e\u043b\u0442\u04af\u0441\u0442\u0456\u043a \u0410\u043c\u0435\u0440\u0438\u043a\u0430",
            "Link": "https://kk.wikipedia.org/wiki/%D0%A1%D0%BE%D0%BB%D1%82%D2%AF%D1%81%D1%82%D1%96%D0%BA_%D0%90%D0%BC%D0%B5%D1%80%D0%B8%D0%BA%D0%B0"
        },
        "km": {
            "Title": "\u17a2\u17b6\u1798\u17c1\u179a\u17b7\u1780\u1781\u17b6\u1784\u1787\u17be\u1784",
            "Link": "https://km.wikipedia.org/wiki/%E1%9E%A2%E1%9E%B6%E1%9E%98%E1%9F%81%E1%9E%9A%E1%9E%B7%E1%9E%80%E1%9E%81%E1%9E%B6%E1%9E%84%E1%9E%87%E1%9E%BE%E1%9E%84"
        },
        "kn": {
            "Title": "\u0c89\u0ca4\u0ccd\u0ca4\u0cb0 \u0c85\u0cae\u0cc7\u0cb0\u0cbf\u0c95",
            "Link": "https://kn.wikipedia.org/wiki/%E0%B2%89%E0%B2%A4%E0%B3%8D%E0%B2%A4%E0%B2%B0_%E0%B2%85%E0%B2%AE%E0%B3%87%E0%B2%B0%E0%B2%BF%E0%B2%95"
        },
        "koi": {
            "Title": "\u041e\u0439\u0432\u044b\u0432 \u0410\u043c\u0435\u0440\u0438\u043a\u0430",
            "Link": "https://koi.wikipedia.org/wiki/%D0%9E%D0%B9%D0%B2%D1%8B%D0%B2_%D0%90%D0%BC%D0%B5%D1%80%D0%B8%D0%BA%D0%B0"
        },
        "ko": {
            "Title": "\ubd84\ub958:\ubd81\uc544\uba54\ub9ac\uce74",
            "Link": "https://ko.wikinews.org/wiki/%EB%B6%84%EB%A5%98:%EB%B6%81%EC%95%84%EB%A9%94%EB%A6%AC%EC%B9%B4"
        },
        "krc": {
            "Title": "\u0428\u0438\u043c\u0430\u043b \u0410\u043c\u0435\u0440\u0438\u043a\u0430",
            "Link": "https://krc.wikipedia.org/wiki/%D0%A8%D0%B8%D0%BC%D0%B0%D0%BB_%D0%90%D0%BC%D0%B5%D1%80%D0%B8%D0%BA%D0%B0"
        },
        "ks": {
            "Title": "\u0634\u064f\u0645\u0672\u0644\u06cc \u0627\u0645\u0631\u06cc\u06a9\u06c1",
            "Link": "https://ks.wikipedia.org/wiki/%D8%B4%D9%8F%D9%85%D9%B2%D9%84%DB%8C_%D8%A7%D9%85%D8%B1%DB%8C%DA%A9%DB%81"
        },
        "ku": {
            "Title": "Amer\u00eekaya Bakur",
            "Link": "https://ku.wikipedia.org/wiki/Amer%C3%AEkaya_Bakur"
        },
        "kv": {
            "Title": "\u0412\u043e\u0439\u0432\u044b\u0432 \u0410\u043c\u0435\u0440\u0438\u043a\u0430",
            "Link": "https://kv.wikipedia.org/wiki/%D0%92%D0%BE%D0%B9%D0%B2%D1%8B%D0%B2_%D0%90%D0%BC%D0%B5%D1%80%D0%B8%D0%BA%D0%B0"
        },
        "kw": {
            "Title": "Amerika Gledh",
            "Link": "https://kw.wikipedia.org/wiki/Amerika_Gledh"
        },
        "ky": {
            "Title": "\u0422\u04af\u043d\u0434\u04af\u043a \u0410\u043c\u0435\u0440\u0438\u043a\u0430",
            "Link": "https://ky.wikipedia.org/wiki/%D0%A2%D2%AF%D0%BD%D0%B4%D2%AF%D0%BA_%D0%90%D0%BC%D0%B5%D1%80%D0%B8%D0%BA%D0%B0"
        },
        "lad": {
            "Title": "Amerika del Norte",
            "Link": "https://lad.wikipedia.org/wiki/Amerika_del_Norte"
        },
        "la": {
            "Title": "America Septentrionalis",
            "Link": "https://la.wikipedia.org/wiki/America_Septentrionalis"
        },
        "lb": {
            "Title": "Nord- a M\u00ebttelamerika",
            "Link": "https://lb.wikipedia.org/wiki/Nord-_a_M%C3%ABttelamerika"
        },
        "lez": {
            "Title": "\u041a\u0435\u0444\u0435\u0440\u043f\u0430\u0442\u0430\u043d \u0410\u043c\u0435\u0440\u0438\u043a\u0430",
            "Link": "https://lez.wikipedia.org/wiki/%D0%9A%D0%B5%D1%84%D0%B5%D1%80%D0%BF%D0%B0%D1%82%D0%B0%D0%BD_%D0%90%D0%BC%D0%B5%D1%80%D0%B8%D0%BA%D0%B0"
        },
        "lfn": {
            "Title": "America Norde",
            "Link": "https://lfn.wikipedia.org/wiki/America_Norde"
        },
        "lg": {
            "Title": "North America",
            "Link": "https://lg.wikipedia.org/wiki/North_America"
        },
        "lij": {
            "Title": "America do N\u00f2rd",
            "Link": "https://lij.wikipedia.org/wiki/America_do_N%C3%B2rd"
        },
        "li": {
            "Title": "Noord-Amerika",
            "Link": "https://li.wikipedia.org/wiki/Noord-Amerika"
        },
        "lld": {
            "Title": "America dl Nord",
            "Link": "https://lld.wikipedia.org/wiki/America_dl_Nord"
        },
        "lmo": {
            "Title": "America del Nord",
            "Link": "https://lmo.wikipedia.org/wiki/America_del_Nord"
        },
        "lo": {
            "Title": "\u0e97\u0eb0\u0ea7\u0eb5\u0e9a\u0ead\u0eb2\u0ec0\u0ea1\u0ea3\u0eb4\u0e81\u0eb2\u0ec0\u0edc\u0eb7\u0ead",
            "Link": "https://lo.wikipedia.org/wiki/%E0%BA%97%E0%BA%B0%E0%BA%A7%E0%BA%B5%E0%BA%9A%E0%BA%AD%E0%BA%B2%E0%BB%80%E0%BA%A1%E0%BA%A3%E0%BA%B4%E0%BA%81%E0%BA%B2%E0%BB%80%E0%BB%9C%E0%BA%B7%E0%BA%AD"
        },
        "lt": {
            "Title": "\u0160iaur\u0117s Amerika",
            "Link": "https://lt.wikipedia.org/wiki/%C5%A0iaur%C4%97s_Amerika"
        },
        "lv": {
            "Title": "Zieme\u013camerika",
            "Link": "https://lv.wikipedia.org/wiki/Zieme%C4%BCamerika"
        },
        "mai": {
            "Title": "\u0909\u0924\u094d\u0924\u0930 \u0905\u092e\u0947\u0930\u093f\u0915\u093e",
            "Link": "https://mai.wikipedia.org/wiki/%E0%A4%89%E0%A4%A4%E0%A5%8D%E0%A4%A4%E0%A4%B0_%E0%A4%85%E0%A4%AE%E0%A5%87%E0%A4%B0%E0%A4%BF%E0%A4%95%E0%A4%BE"
        },
        "jv-x-bms": {
            "Title": "Amerika Lor",
            "Link": "https://map-bms.wikipedia.org/wiki/Amerika_Lor"
        },
        "mdf": {
            "Title": "\u041a\u0435\u043b\u044c\u043c\u0435\u0448\u0438\u0440\u0435\u043d\u044c \u0410\u043c\u0435\u0440\u0438\u043a\u0430\u0441\u044c",
            "Link": "https://mdf.wikipedia.org/wiki/%D0%9A%D0%B5%D0%BB%D1%8C%D0%BC%D0%B5%D1%88%D0%B8%D1%80%D0%B5%D0%BD%D1%8C_%D0%90%D0%BC%D0%B5%D1%80%D0%B8%D0%BA%D0%B0%D1%81%D1%8C"
        },
        "mhr": {
            "Title": "\u0419\u04f1\u0434\u0432\u0435\u043b \u0410\u043c\u0435\u0440\u0438\u043a\u0430",
            "Link": "https://mhr.wikipedia.org/wiki/%D0%99%D3%B1%D0%B4%D0%B2%D0%B5%D0%BB_%D0%90%D0%BC%D0%B5%D1%80%D0%B8%D0%BA%D0%B0"
        },
        "min": {
            "Title": "Amerika Utara",
            "Link": "https://min.wikipedia.org/wiki/Amerika_Utara"
        },
        "mi": {
            "Title": "Amerika-ki-te-Raki",
            "Link": "https://mi.wikipedia.org/wiki/Amerika-ki-te-Raki"
        },
        "mk": {
            "Title": "\u0421\u0435\u0432\u0435\u0440\u043d\u0430 \u0410\u043c\u0435\u0440\u0438\u043a\u0430",
            "Link": "https://mk.wikipedia.org/wiki/%D0%A1%D0%B5%D0%B2%D0%B5%D1%80%D0%BD%D0%B0_%D0%90%D0%BC%D0%B5%D1%80%D0%B8%D0%BA%D0%B0"
        },
        "ml": {
            "Title": "\u0d35\u0d1f\u0d15\u0d4d\u0d15\u0d47 \u0d05\u0d2e\u0d47\u0d30\u0d3f\u0d15\u0d4d\u0d15",
            "Link": "https://ml.wikipedia.org/wiki/%E0%B4%B5%E0%B4%9F%E0%B4%95%E0%B5%8D%E0%B4%95%E0%B5%87_%E0%B4%85%E0%B4%AE%E0%B5%87%E0%B4%B0%E0%B4%BF%E0%B4%95%E0%B5%8D%E0%B4%95"
        },
        "mni": {
            "Title": "\uabd1\uabcb\uabe5\uabe1 \uabd1\uabc3\uabe6\uabd4\uabe4\uabc0\uabe5",
            "Link": "https://mni.wikipedia.org/wiki/%EA%AF%91%EA%AF%8B%EA%AF%A5%EA%AF%A1_%EA%AF%91%EA%AF%83%EA%AF%A6%EA%AF%94%EA%AF%A4%EA%AF%80%EA%AF%A5"
        },
        "mn": {
            "Title": "\u0425\u043e\u0439\u0434 \u0410\u043c\u0435\u0440\u0438\u043a",
            "Link": "https://mn.wikipedia.org/wiki/%D0%A5%D0%BE%D0%B9%D0%B4_%D0%90%D0%BC%D0%B5%D1%80%D0%B8%D0%BA"
        },
        "mnw": {
            "Title": "\u1021\u1019\u1031\u101b\u102d\u1000\u101e\u105f\u101d\u103a\u1000\u103b\u102c",
            "Link": "https://mnw.wikipedia.org/wiki/%E1%80%A1%E1%80%99%E1%80%B1%E1%80%9B%E1%80%AD%E1%80%80%E1%80%9E%E1%81%9F%E1%80%9D%E1%80%BA%E1%80%80%E1%80%BB%E1%80%AC"
        },
        "ms": {
            "Title": "Amerika Utara",
            "Link": "https://ms.wikipedia.org/wiki/Amerika_Utara"
        },
        "mt": {
            "Title": "L-Amerika ta' Fuq",
            "Link": "https://mt.wikipedia.org/wiki/L-Amerika_ta%27_Fuq"
        },
        "mwl": {
            "Title": "Am\u00e9rica de l Norte",
            "Link": "https://mwl.wikipedia.org/wiki/Am%C3%A9rica_de_l_Norte"
        },
        "myv": {
            "Title": "\u041f\u0435\u043b\u0435\u0432\u0435\u0451\u043d\u043a\u0441\u043e\u043d\u044c \u0410\u043c\u0435\u0440\u0438\u043a\u0430",
            "Link": "https://myv.wikipedia.org/wiki/%D0%9F%D0%B5%D0%BB%D0%B5%D0%B2%D0%B5%D1%91%D0%BD%D0%BA%D1%81%D0%BE%D0%BD%D1%8C_%D0%90%D0%BC%D0%B5%D1%80%D0%B8%D0%BA%D0%B0"
        },
        "my": {
            "Title": "\u1019\u103c\u1031\u102c\u1000\u103a\u1021\u1019\u1031\u101b\u102d\u1000",
            "Link": "https://my.wikipedia.org/wiki/%E1%80%99%E1%80%BC%E1%80%B1%E1%80%AC%E1%80%80%E1%80%BA%E1%80%A1%E1%80%99%E1%80%B1%E1%80%9B%E1%80%AD%E1%80%80"
        },
        "mzn": {
            "Title": "\u0634\u0645\u0627\u0644\u06cc \u0627\u0645\u0631\u06cc\u06a9\u0627",
            "Link": "https://mzn.wikipedia.org/wiki/%D8%B4%D9%85%D8%A7%D9%84%DB%8C_%D8%A7%D9%85%D8%B1%DB%8C%DA%A9%D8%A7"
        },
        "nap": {
            "Title": "Nordam\u00e8reca",
            "Link": "https://nap.wikipedia.org/wiki/Nordam%C3%A8reca"
        },
        "nds-NL": {
            "Title": "Noord-Amerika",
            "Link": "https://nds-nl.wikipedia.org/wiki/Noord-Amerika"
        },
        "nds": {
            "Title": "Noordamerika",
            "Link": "https://nds.wikipedia.org/wiki/Noordamerika"
        },
        "ne": {
            "Title": "\u0909\u0924\u094d\u0924\u0930 \u0905\u092e\u0947\u0930\u093f\u0915\u093e",
            "Link": "https://ne.wikipedia.org/wiki/%E0%A4%89%E0%A4%A4%E0%A5%8D%E0%A4%A4%E0%A4%B0_%E0%A4%85%E0%A4%AE%E0%A5%87%E0%A4%B0%E0%A4%BF%E0%A4%95%E0%A4%BE"
        },
        "new": {
            "Title": "\u0909\u0924\u094d\u0924\u0930 \u0905\u092e\u0947\u0930\u093f\u0915\u093e",
            "Link": "https://new.wikipedia.org/wiki/%E0%A4%89%E0%A4%A4%E0%A5%8D%E0%A4%A4%E0%A4%B0_%E0%A4%85%E0%A4%AE%E0%A5%87%E0%A4%B0%E0%A4%BF%E0%A4%95%E0%A4%BE"
        },
        "nl": {
            "Title": "Noord-Amerika",
            "Link": "https://nl.wikivoyage.org/wiki/Noord-Amerika"
        },
        "nn": {
            "Title": "Nord-Amerika",
            "Link": "https://nn.wikipedia.org/wiki/Nord-Amerika"
        },
        "nov": {
            "Title": "Nordi Amerika",
            "Link": "https://nov.wikipedia.org/wiki/Nordi_Amerika"
        },
        "no": {
            "Title": "Kategori:Nord-Amerika",
            "Link": "https://no.wikinews.org/wiki/Kategori:Nord-Amerika"
        },
        "nrf": {
            "Title": "Am\u00e9thique du Nord",
            "Link": "https://nrm.wikipedia.org/wiki/Am%C3%A9thique_du_Nord"
        },
        "nso": {
            "Title": "Amerika Leboa",
            "Link": "https://nso.wikipedia.org/wiki/Amerika_Leboa"
        },
        "ny": {
            "Title": "North America",
            "Link": "https://ny.wikipedia.org/wiki/North_America"
        },
        "oc": {
            "Title": "America del N\u00f2rd",
            "Link": "https://oc.wikipedia.org/wiki/America_del_N%C3%B2rd"
        },
        "olo": {
            "Title": "Pohjas-Amerikku",
            "Link": "https://olo.wikipedia.org/wiki/Pohjas-Amerikku"
        },
        "om": {
            "Title": "Ameerikaa Kaabaa",
            "Link": "https://om.wikipedia.org/wiki/Ameerikaa_Kaabaa"
        },
        "or": {
            "Title": "\u0b09\u0b24\u0b4d\u0b24\u0b30 \u0b06\u0b2e\u0b47\u0b30\u0b3f\u0b15\u0b3e",
            "Link": "https://or.wikipedia.org/wiki/%E0%AC%89%E0%AC%A4%E0%AD%8D%E0%AC%A4%E0%AC%B0_%E0%AC%86%E0%AC%AE%E0%AD%87%E0%AC%B0%E0%AC%BF%E0%AC%95%E0%AC%BE"
        },
        "os": {
            "Title": "\u0426\u00e6\u0433\u0430\u0442 \u0410\u043c\u0435\u0440\u0438\u043a\u00e6",
            "Link": "https://os.wikipedia.org/wiki/%D0%A6%C3%A6%D0%B3%D0%B0%D1%82_%D0%90%D0%BC%D0%B5%D1%80%D0%B8%D0%BA%C3%A6"
        },
        "pam": {
            "Title": "Pang\u00falung Amerika",
            "Link": "https://pam.wikipedia.org/wiki/Pang%C3%BAlung_Amerika"
        },
        "pap": {
            "Title": "Nort Am\u00e9rika",
            "Link": "https://pap.wikipedia.org/wiki/Nort_Am%C3%A9rika"
        },
        "pa": {
            "Title": "\u0a09\u0a71\u0a24\u0a30\u0a40 \u0a05\u0a2e\u0a30\u0a40\u0a15\u0a3e",
            "Link": "https://pa.wikipedia.org/wiki/%E0%A8%89%E0%A9%B1%E0%A8%A4%E0%A8%B0%E0%A9%80_%E0%A8%85%E0%A8%AE%E0%A8%B0%E0%A9%80%E0%A8%95%E0%A8%BE"
        },
        "pcd": {
            "Title": "Anm\u00e9rike du Nord",
            "Link": "https://pcd.wikipedia.org/wiki/Anm%C3%A9rike_du_Nord"
        },
        "pdc": {
            "Title": "Nard-Amerikaa",
            "Link": "https://pdc.wikipedia.org/wiki/Nard-Amerikaa"
        },
        "pih": {
            "Title": "North Merika",
            "Link": "https://pih.wikipedia.org/wiki/North_Merika"
        },
        "pl": {
            "Title": "Ameryka P\u00f3\u0142nocna",
            "Link": "https://pl.wikivoyage.org/wiki/Ameryka_P%C3%B3%C5%82nocna"
        },
        "pnb": {
            "Title": "\u0627\u064f\u0628\u06be\u0627 \u0627\u0645\u0631\u06cc\u06a9\u0627",
            "Link": "https://pnb.wikipedia.org/wiki/%D8%A7%D9%8F%D8%A8%DA%BE%D8%A7_%D8%A7%D9%85%D8%B1%DB%8C%DA%A9%D8%A7"
        },
        "ps": {
            "Title": "\u0634\u0645\u0627\u0644\u064a \u0627\u0645\u0631\u064a\u06a9\u0627",
            "Link": "https://ps.wikipedia.org/wiki/%D8%B4%D9%85%D8%A7%D9%84%D9%8A_%D8%A7%D9%85%D8%B1%D9%8A%DA%A9%D8%A7"
        },
        "pt": {
            "Title": "Am\u00e9rica do Norte",
            "Link": "https://pt.wikivoyage.org/wiki/Am%C3%A9rica_do_Norte"
        },
        "rm": {
            "Title": "America dal Nord",
            "Link": "https://rm.wikipedia.org/wiki/America_dal_Nord"
        },
        "rmy": {
            "Title": "Nordutni Amerika",
            "Link": "https://rmy.wikipedia.org/wiki/Nordutni_Amerika"
        },
        "rup": {
            "Title": "America di Nord",
            "Link": "https://roa-rup.wikipedia.org/wiki/America_di_Nord"
        },
        "nap-x-tara": {
            "Title": "Americhe settendrionale",
            "Link": "https://roa-tara.wikipedia.org/wiki/Americhe_settendrionale"
        },
        "ro": {
            "Title": "America de Nord",
            "Link": "https://ro.wikivoyage.org/wiki/America_de_Nord"
        },
        "rue": {
            "Title": "\u0421\u0435\u0432\u0435\u0440\u043d\u0430 \u0410\u043c\u0435\u0440\u0438\u043a\u0430",
            "Link": "https://rue.wikipedia.org/wiki/%D0%A1%D0%B5%D0%B2%D0%B5%D1%80%D0%BD%D0%B0_%D0%90%D0%BC%D0%B5%D1%80%D0%B8%D0%BA%D0%B0"
        },
        "ru": {
            "Title": "\u0421\u0435\u0432\u0435\u0440\u043d\u0430\u044f \u0410\u043c\u0435\u0440\u0438\u043a\u0430",
            "Link": "https://ru.wikivoyage.org/wiki/%D0%A1%D0%B5%D0%B2%D0%B5%D1%80%D0%BD%D0%B0%D1%8F_%D0%90%D0%BC%D0%B5%D1%80%D0%B8%D0%BA%D0%B0"
        },
        "rw": {
            "Title": "Amerika ya Ruguru",
            "Link": "https://rw.wikipedia.org/wiki/Amerika_ya_Ruguru"
        },
        "sah": {
            "Title": "\u0425\u043e\u0442\u0443 \u0410\u043c\u0435\u0440\u0438\u043a\u0430",
            "Link": "https://sah.wikipedia.org/wiki/%D0%A5%D0%BE%D1%82%D1%83_%D0%90%D0%BC%D0%B5%D1%80%D0%B8%D0%BA%D0%B0"
        },
        "sat": {
            "Title": "\u1c60\u1c5a\u1c67\u1c6e \u1c5f\u1c62\u1c6e\u1c68\u1c64\u1c60\u1c5f",
            "Link": "https://sat.wikipedia.org/wiki/%E1%B1%A0%E1%B1%9A%E1%B1%A7%E1%B1%AE_%E1%B1%9F%E1%B1%A2%E1%B1%AE%E1%B1%A8%E1%B1%A4%E1%B1%A0%E1%B1%9F"
        },
        "sa": {
            "Title": "\u0909\u0924\u094d\u0924\u0930-\u0905\u092e\u0947\u0930\u093f\u0915\u093e\u0916\u0923\u094d\u0921\u0903",
            "Link": "https://sa.wikipedia.org/wiki/%E0%A4%89%E0%A4%A4%E0%A5%8D%E0%A4%A4%E0%A4%B0-%E0%A4%85%E0%A4%AE%E0%A5%87%E0%A4%B0%E0%A4%BF%E0%A4%95%E0%A4%BE%E0%A4%96%E0%A4%A3%E0%A5%8D%E0%A4%A1%E0%A4%83"
        },
        "scn": {
            "Title": "Am\u00e8rica d\u00fb Nord",
            "Link": "https://scn.wikipedia.org/wiki/Am%C3%A8rica_d%C3%BB_Nord"
        },
        "sco": {
            "Title": "North Americae",
            "Link": "https://sco.wikipedia.org/wiki/North_Americae"
        },
        "sd": {
            "Title": "\u0627\u062a\u0631 \u0622\u0645\u0631\u064a\u06aa\u0627",
            "Link": "https://sd.wikipedia.org/wiki/%D8%A7%D8%AA%D8%B1_%D8%A2%D9%85%D8%B1%D9%8A%DA%AA%D8%A7"
        },
        "se": {
            "Title": "Davvi-Amerihkk\u00e1",
            "Link": "https://se.wikipedia.org/wiki/Davvi-Amerihkk%C3%A1"
        },
        "shn": {
            "Title": "\u1022\u1019\u1084\u1087\u101b\u102d\u1075\u1081\u103d\u1004\u103a\u1087",
            "Link": "https://shn.wikipedia.org/wiki/%E1%80%A2%E1%80%99%E1%82%84%E1%82%87%E1%80%9B%E1%80%AD%E1%81%B5%E1%82%81%E1%80%BD%E1%80%84%E1%80%BA%E1%82%87"
        },
        "sh": {
            "Title": "Sjeverna Amerika",
            "Link": "https://sh.wikipedia.org/wiki/Sjeverna_Amerika"
        },
        "en-simple": {
            "Title": "North America",
            "Link": "https://simple.wikipedia.org/wiki/North_America"
        },
        "si": {
            "Title": "\u0d8b\u0dad\u0dd4\u0dbb\u0dd4 \u0d87\u0db8\u0dd9\u0dbb\u0dd2\u0d9a\u0dcf\u0dc0",
            "Link": "https://si.wikipedia.org/wiki/%E0%B6%8B%E0%B6%AD%E0%B7%94%E0%B6%BB%E0%B7%94_%E0%B6%87%E0%B6%B8%E0%B7%99%E0%B6%BB%E0%B7%92%E0%B6%9A%E0%B7%8F%E0%B7%80"
        },
        "skr": {
            "Title": "\u0634\u0645\u0627\u0644\u06cc \u0627\u0645\u0631\u06cc\u06a9\u06c1",
            "Link": "https://skr.wikipedia.org/wiki/%D8%B4%D9%85%D8%A7%D9%84%DB%8C_%D8%A7%D9%85%D8%B1%DB%8C%DA%A9%DB%81"
        },
        "sk": {
            "Title": "Severn\u00e1 Amerika",
            "Link": "https://sk.wikipedia.org/wiki/Severn%C3%A1_Amerika"
        },
        "sl": {
            "Title": "Severna Amerika",
            "Link": "https://sl.wikipedia.org/wiki/Severna_Amerika"
        },
        "smn": {
            "Title": "Tave-Amerik",
            "Link": "https://smn.wikipedia.org/wiki/Tave-Amerik"
        },
        "sm": {
            "Title": "Amerika i Matu",
            "Link": "https://sm.wikipedia.org/wiki/Amerika_i_Matu"
        },
        "sn": {
            "Title": "Amerika Maodzanyemba",
            "Link": "https://sn.wikipedia.org/wiki/Amerika_Maodzanyemba"
        },
        "so": {
            "Title": "Woqooyiga Ameerika",
            "Link": "https://so.wikipedia.org/wiki/Woqooyiga_Ameerika"
        },
        "sq": {
            "Title": "Kategoria:Amerik\u00eb Veriore",
            "Link": "https://sq.wikinews.org/wiki/Kategoria:Amerik%C3%AB_Veriore"
        },
        "srn": {
            "Title": "Opo Amrika",
            "Link": "https://srn.wikipedia.org/wiki/Opo_Amrika"
        },
        "sr": {
            "Title": "\u0421\u0435\u0432\u0435\u0440\u043d\u0430 \u0410\u043c\u0435\u0440\u0438\u043a\u0430",
            "Link": "https://sr.wikiquote.org/wiki/%D0%A1%D0%B5%D0%B2%D0%B5%D1%80%D0%BD%D0%B0_%D0%90%D0%BC%D0%B5%D1%80%D0%B8%D0%BA%D0%B0"
        },
        "stq": {
            "Title": "Noudamerikoa",
            "Link": "https://stq.wikipedia.org/wiki/Noudamerikoa"
        },
        "st": {
            "Title": "Amerika Leboya",
            "Link": "https://st.wikipedia.org/wiki/Amerika_Leboya"
        },
        "su": {
            "Title": "Am\u00e9rika Kal\u00e9r",
            "Link": "https://su.wikipedia.org/wiki/Am%C3%A9rika_Kal%C3%A9r"
        },
        "sv": {
            "Title": "Nordamerika",
            "Link": "https://sv.wikivoyage.org/wiki/Nordamerika"
        },
        "sw": {
            "Title": "Amerika ya Kaskazini",
            "Link": "https://sw.wikipedia.org/wiki/Amerika_ya_Kaskazini"
        },
        "szl": {
            "Title": "P\u016f\u0142nocno Amerika",
            "Link": "https://szl.wikipedia.org/wiki/P%C5%AF%C5%82nocno_Amerika"
        },
        "ta": {
            "Title": "\u0baa\u0b95\u0bc1\u0baa\u0bcd\u0baa\u0bc1:\u0bb5\u0b9f \u0b85\u0bae\u0bc6\u0bb0\u0bbf\u0b95\u0bcd\u0b95\u0bbe",
            "Link": "https://ta.wikinews.org/wiki/%E0%AE%AA%E0%AE%95%E0%AF%81%E0%AE%AA%E0%AF%8D%E0%AE%AA%E0%AF%81:%E0%AE%B5%E0%AE%9F_%E0%AE%85%E0%AE%AE%E0%AF%86%E0%AE%B0%E0%AE%BF%E0%AE%95%E0%AF%8D%E0%AE%95%E0%AE%BE"
        },
        "tay": {
            "Title": "Pemeco",
            "Link": "https://tay.wikipedia.org/wiki/Pemeco"
        },
        "tcy": {
            "Title": "\u0c89\u0ca4\u0ccd\u0ca4\u0cb0 \u0c85\u0cae\u0cc7\u0cb0\u0cbf\u0c95",
            "Link": "https://tcy.wikipedia.org/wiki/%E0%B2%89%E0%B2%A4%E0%B3%8D%E0%B2%A4%E0%B2%B0_%E0%B2%85%E0%B2%AE%E0%B3%87%E0%B2%B0%E0%B2%BF%E0%B2%95"
        },
        "te": {
            "Title": "\u0c09\u0c24\u0c4d\u0c24\u0c30 \u0c05\u0c2e\u0c46\u0c30\u0c3f\u0c15\u0c3e",
            "Link": "https://te.wikipedia.org/wiki/%E0%B0%89%E0%B0%A4%E0%B1%8D%E0%B0%A4%E0%B0%B0_%E0%B0%85%E0%B0%AE%E0%B1%86%E0%B0%B0%E0%B0%BF%E0%B0%95%E0%B0%BE"
        },
        "tg": {
            "Title": "\u0410\u043c\u0440\u0438\u043a\u043e\u0438 \u0428\u0438\u043c\u043e\u043b\u04e3",
            "Link": "https://tg.wikipedia.org/wiki/%D0%90%D0%BC%D1%80%D0%B8%D0%BA%D0%BE%D0%B8_%D0%A8%D0%B8%D0%BC%D0%BE%D0%BB%D3%A3"
        },
        "th": {
            "Title": "\u0e17\u0e27\u0e35\u0e1b\u0e2d\u0e40\u0e21\u0e23\u0e34\u0e01\u0e32\u0e40\u0e2b\u0e19\u0e37\u0e2d",
            "Link": "https://th.wikipedia.org/wiki/%E0%B8%97%E0%B8%A7%E0%B8%B5%E0%B8%9B%E0%B8%AD%E0%B9%80%E0%B8%A1%E0%B8%A3%E0%B8%B4%E0%B8%81%E0%B8%B2%E0%B9%80%E0%B8%AB%E0%B8%99%E0%B8%B7%E0%B8%AD"
        },
        "tk": {
            "Title": "Demirgazyk Amerika",
            "Link": "https://tk.wikipedia.org/wiki/Demirgazyk_Amerika"
        },
        "tl": {
            "Title": "Hilagang Amerika",
            "Link": "https://tl.wikipedia.org/wiki/Hilagang_Amerika"
        },
        "tly": {
            "Title": "Kob\u0259son\u0259 Amerik\u0259",
            "Link": "https://tly.wikipedia.org/wiki/Kob%C9%99son%C9%99_Amerik%C9%99"
        },
        "tpi": {
            "Title": "Not Amerika",
            "Link": "https://tpi.wikipedia.org/wiki/Not_Amerika"
        },
        "tr": {
            "Title": "Kuzey Amerika",
            "Link": "https://tr.wikivoyage.org/wiki/Kuzey_Amerika"
        },
        "ts": {
            "Title": "Amerikha ya le N'walungu",
            "Link": "https://ts.wikipedia.org/wiki/Amerikha_ya_le_N%27walungu"
        },
        "tt": {
            "Title": "\u0422\u04e9\u043d\u044c\u044f\u043a \u0410\u043c\u0435\u0440\u0438\u043a\u0430",
            "Link": "https://tt.wikipedia.org/wiki/%D0%A2%D3%A9%D0%BD%D1%8C%D1%8F%D0%BA_%D0%90%D0%BC%D0%B5%D1%80%D0%B8%D0%BA%D0%B0"
        },
        "tum": {
            "Title": "Amelika wa Kumpoto",
            "Link": "https://tum.wikipedia.org/wiki/Amelika_wa_Kumpoto"
        },
        "tyv": {
            "Title": "\u0421\u043e\u04a3\u0433\u0443 \u0410\u043c\u0435\u0440\u0438\u043a\u0430",
            "Link": "https://tyv.wikipedia.org/wiki/%D0%A1%D0%BE%D2%A3%D0%B3%D1%83_%D0%90%D0%BC%D0%B5%D1%80%D0%B8%D0%BA%D0%B0"
        },
        "udm": {
            "Title": "\u0423\u0439\u043f\u0430\u043b \u0410\u043c\u0435\u0440\u0438\u043a\u0430",
            "Link": "https://udm.wikipedia.org/wiki/%D0%A3%D0%B9%D0%BF%D0%B0%D0%BB_%D0%90%D0%BC%D0%B5%D1%80%D0%B8%D0%BA%D0%B0"
        },
        "ug": {
            "Title": "\u0634\u0649\u0645\u0627\u0644\u0649\u064a \u0626\u0627\u0645\u06d0\u0631\u0649\u0643\u0627",
            "Link": "https://ug.wikipedia.org/wiki/%D8%B4%D9%89%D9%85%D8%A7%D9%84%D9%89%D9%8A_%D8%A6%D8%A7%D9%85%DB%90%D8%B1%D9%89%D9%83%D8%A7"
        },
        "uk": {
            "Title": "\u041f\u0456\u0432\u043d\u0456\u0447\u043d\u0430 \u0410\u043c\u0435\u0440\u0438\u043a\u0430",
            "Link": "https://uk.wikivoyage.org/wiki/%D0%9F%D1%96%D0%B2%D0%BD%D1%96%D1%87%D0%BD%D0%B0_%D0%90%D0%BC%D0%B5%D1%80%D0%B8%D0%BA%D0%B0"
        },
        "ur": {
            "Title": "\u0634\u0645\u0627\u0644\u06cc \u0627\u0645\u0631\u06cc\u06a9\u0627",
            "Link": "https://ur.wikipedia.org/wiki/%D8%B4%D9%85%D8%A7%D9%84%DB%8C_%D8%A7%D9%85%D8%B1%DB%8C%DA%A9%D8%A7"
        },
        "uz": {
            "Title": "Shimoliy Amerika",
            "Link": "https://uz.wikipedia.org/wiki/Shimoliy_Amerika"
        },
        "vec": {
            "Title": "Am\u00e8rica del Nord",
            "Link": "https://vec.wikipedia.org/wiki/Am%C3%A8rica_del_Nord"
        },
        "vep": {
            "Title": "Pohjoi\u017eamerik",
            "Link": "https://vep.wikipedia.org/wiki/Pohjoi%C5%BEamerik"
        },
        "vi": {
            "Title": "B\u1eafc M\u1ef9",
            "Link": "https://vi.wikivoyage.org/wiki/B%E1%BA%AFc_M%E1%BB%B9"
        },
        "vls": {
            "Title": "N\u00f4ord-Amerika",
            "Link": "https://vls.wikipedia.org/wiki/N%C3%B4ord-Amerika"
        },
        "vo": {
            "Title": "Nol\u00fcda-Merop",
            "Link": "https://vo.wikipedia.org/wiki/Nol%C3%BCda-Merop"
        },
        "war": {
            "Title": "Amihanan nga Amerika",
            "Link": "https://war.wikipedia.org/wiki/Amihanan_nga_Amerika"
        },
        "wa": {
            "Title": "Amerike bijhrece",
            "Link": "https://wa.wikipedia.org/wiki/Amerike_bijhrece"
        },
        "wuu": {
            "Title": "\u5317\u7f8e\u6d32",
            "Link": "https://wuu.wikipedia.org/wiki/%E5%8C%97%E7%BE%8E%E6%B4%B2"
        },
        "xh": {
            "Title": "UmNtla Melika",
            "Link": "https://xh.wikipedia.org/wiki/UmNtla_Melika"
        },
        "xmf": {
            "Title": "\u10dd\u10dd\u10e0\u10e3\u10d4 \u10d0\u10db\u10d4\u10e0\u10d8\u10d9\u10d0",
            "Link": "https://xmf.wikipedia.org/wiki/%E1%83%9D%E1%83%9D%E1%83%A0%E1%83%A3%E1%83%94_%E1%83%90%E1%83%9B%E1%83%94%E1%83%A0%E1%83%98%E1%83%99%E1%83%90"
        },
        "yi": {
            "Title": "\u05e6\u05e4\u05d5\u05df \u05d0\u05de\u05e2\u05e8\u05d9\u05e7\u05e2",
            "Link": "https://yi.wikipedia.org/wiki/%D7%A6%D7%A4%D7%95%D7%9F_%D7%90%D7%9E%D7%A2%D7%A8%D7%99%D7%A7%D7%A2"
        },
        "yo": {
            "Title": "\u00c0r\u00edw\u00e1 Am\u1eb9\u0301r\u00edk\u00e0",
            "Link": "https://yo.wikipedia.org/wiki/%C3%80r%C3%ADw%C3%A1_Am%E1%BA%B9%CC%81r%C3%ADk%C3%A0"
        },
        "za": {
            "Title": "Baekmeijcouh",
            "Link": "https://za.wikipedia.org/wiki/Baekmeijcouh"
        },
        "zea": {
            "Title": "No\u00f4rd-Amerika",
            "Link": "https://zea.wikipedia.org/wiki/No%C3%B4rd-Amerika"
        },
        "zgh": {
            "Title": "\u2d49\u2d65\u2d65\u2d4d\u2d4e\u2d39 \u2d4f \u2d30\u2d4e\u2d54\u2d49\u2d3d\u2d30",
            "Link": "https://zgh.wikipedia.org/wiki/%E2%B5%89%E2%B5%A5%E2%B5%A5%E2%B5%8D%E2%B5%8E%E2%B4%B9_%E2%B5%8F_%E2%B4%B0%E2%B5%8E%E2%B5%94%E2%B5%89%E2%B4%BD%E2%B4%B0"
        },
        "nan": {
            "Title": "Pak B\u00ed-chiu",
            "Link": "https://zh-min-nan.wikipedia.org/wiki/Pak_B%C3%AD-chiu"
        },
        "yue": {
            "Title": "\u5317\u7f8e\u6d32",
            "Link": "https://zh-yue.wikipedia.org/wiki/%E5%8C%97%E7%BE%8E%E6%B4%B2"
        },
        "zh": {
            "Title": "\u5317\u7f8e\u6d32",
            "Link": "https://zh.wikivoyage.org/wiki/%E5%8C%97%E7%BE%8E%E6%B4%B2"
        },
        "zu": {
            "Title": "IMelika Enyakatho",
            "Link": "https://zu.wikipedia.org/wiki/IMelika_Enyakatho"
        }
    }
}