{
    "Q4421": {
        "af": {
            "Title": "Woud",
            "Link": "https://af.wikipedia.org/wiki/Woud"
        },
        "gsw": {
            "Title": "Wald",
            "Link": "https://als.wikipedia.org/wiki/Wald"
        },
        "ami": {
            "Title": "Kilakilangan",
            "Link": "https://ami.wikipedia.org/wiki/Kilakilangan"
        },
        "am": {
            "Title": "\u132b\u12ab",
            "Link": "https://am.wikipedia.org/wiki/%E1%8C%AB%E1%8A%AB"
        },
        "ang": {
            "Title": "Weald",
            "Link": "https://ang.wikipedia.org/wiki/Weald"
        },
        "an": {
            "Title": "Selva",
            "Link": "https://an.wikipedia.org/wiki/Selva"
        },
        "arc": {
            "Title": "\u0725\u0712\u0710",
            "Link": "https://arc.wikipedia.org/wiki/%DC%A5%DC%92%DC%90"
        },
        "ar": {
            "Title": "\u063a\u0627\u0628\u0629",
            "Link": "https://ar.wikipedia.org/wiki/%D8%BA%D8%A7%D8%A8%D8%A9"
        },
        "ast": {
            "Title": "Viesca",
            "Link": "https://ast.wikipedia.org/wiki/Viesca"
        },
        "as": {
            "Title": "\u0985\u09f0\u09a3\u09cd\u09af",
            "Link": "https://as.wikipedia.org/wiki/%E0%A6%85%E0%A7%B0%E0%A6%A3%E0%A7%8D%E0%A6%AF"
        },
        "awa": {
            "Title": "\u091c\u0902\u0917\u0932",
            "Link": "https://awa.wikipedia.org/wiki/%E0%A4%9C%E0%A4%82%E0%A4%97%E0%A4%B2"
        },
        "azb": {
            "Title": "\u0645\u0626\u0634\u0647",
            "Link": "https://azb.wikipedia.org/wiki/%D9%85%D8%A6%D8%B4%D9%87"
        },
        "az": {
            "Title": "Me\u015f\u0259",
            "Link": "https://az.wikiquote.org/wiki/Me%C5%9F%C9%99"
        },
        "ban": {
            "Title": "Wana",
            "Link": "https://ban.wikipedia.org/wiki/Wana"
        },
        "bar": {
            "Title": "Woid",
            "Link": "https://bar.wikipedia.org/wiki/Woid"
        },
        "sgs": {
            "Title": "Med\u0117",
            "Link": "https://bat-smg.wikipedia.org/wiki/Med%C4%97"
        },
        "ba": {
            "Title": "\u0423\u0440\u043c\u0430\u043d",
            "Link": "https://ba.wikipedia.org/wiki/%D0%A3%D1%80%D0%BC%D0%B0%D0%BD"
        },
        "bcl": {
            "Title": "Kadlagan",
            "Link": "https://bcl.wikipedia.org/wiki/Kadlagan"
        },
        "be-tarask": {
            "Title": "\u041b\u0435\u0441",
            "Link": "https://be-tarask.wikipedia.org/wiki/%D0%9B%D0%B5%D1%81"
        },
        "be": {
            "Title": "\u041b\u0435\u0441",
            "Link": "https://be.wikipedia.org/wiki/%D0%9B%D0%B5%D1%81"
        },
        "bew": {
            "Title": "Utan",
            "Link": "https://bew.wikipedia.org/wiki/Utan"
        },
        "bg": {
            "Title": "\u0413\u043e\u0440\u0430",
            "Link": "https://bg.wikipedia.org/wiki/%D0%93%D0%BE%D1%80%D0%B0"
        },
        "bh": {
            "Title": "\u092c\u0928",
            "Link": "https://bh.wikipedia.org/wiki/%E0%A4%AC%E0%A4%A8"
        },
        "bn": {
            "Title": "\u0985\u09b0\u09a3\u09cd\u09af",
            "Link": "https://bn.wikiquote.org/wiki/%E0%A6%85%E0%A6%B0%E0%A6%A3%E0%A7%8D%E0%A6%AF"
        },
        "br": {
            "Title": "Koadeg",
            "Link": "https://br.wikipedia.org/wiki/Koadeg"
        },
        "bs": {
            "Title": "\u0160uma",
            "Link": "https://bs.wikipedia.org/wiki/%C5%A0uma"
        },
        "bxr": {
            "Title": "\u041e\u0439",
            "Link": "https://bxr.wikipedia.org/wiki/%D0%9E%D0%B9"
        },
        "ca": {
            "Title": "Bosc",
            "Link": "https://ca.wikipedia.org/wiki/Bosc"
        },
        "cdo": {
            "Title": "S\u0115ng-l\u00ecng",
            "Link": "https://cdo.wikipedia.org/wiki/S%C4%95ng-l%C3%ACng"
        },
        "ceb": {
            "Title": "Lasang",
            "Link": "https://ceb.wikipedia.org/wiki/Lasang"
        },
        "ce": {
            "Title": "\u0425\u044c\u0443\u043d",
            "Link": "https://ce.wikipedia.org/wiki/%D0%A5%D1%8C%D1%83%D0%BD"
        },
        "chr": {
            "Title": "\u13a0\u13d9\u13af \u13a2\u13be\u13a8",
            "Link": "https://chr.wikipedia.org/wiki/%E1%8E%A0%E1%8F%99%E1%8E%AF_%E1%8E%A2%E1%8E%BE%E1%8E%A8"
        },
        "ckb": {
            "Title": "\u062f\u0627\u0631\u0633\u062a\u0627\u0646",
            "Link": "https://ckb.wikipedia.org/wiki/%D8%AF%D8%A7%D8%B1%D8%B3%D8%AA%D8%A7%D9%86"
        },
        "crh": {
            "Title": "Orman",
            "Link": "https://crh.wikipedia.org/wiki/Orman"
        },
        "csb": {
            "Title": "Las",
            "Link": "https://csb.wikipedia.org/wiki/Las"
        },
        "cs": {
            "Title": "Les",
            "Link": "https://cs.wikiquote.org/wiki/Les"
        },
        "cv": {
            "Title": "\u0412\u0103\u0440\u043c\u0430\u043d",
            "Link": "https://cv.wikipedia.org/wiki/%D0%92%C4%83%D1%80%D0%BC%D0%B0%D0%BD"
        },
        "cy": {
            "Title": "Coedwig",
            "Link": "https://cy.wikipedia.org/wiki/Coedwig"
        },
        "da": {
            "Title": "Skov",
            "Link": "https://da.wikipedia.org/wiki/Skov"
        },
        "de": {
            "Title": "Wald",
            "Link": "https://de.wikisource.org/wiki/Wald"
        },
        "diq": {
            "Title": "M\u00ea\u015fe",
            "Link": "https://diq.wikipedia.org/wiki/M%C3%AA%C5%9Fe"
        },
        "el": {
            "Title": "\u0394\u03ac\u03c3\u03bf\u03c2",
            "Link": "https://el.wikiquote.org/wiki/%CE%94%CE%AC%CF%83%CE%BF%CF%82"
        },
        "en": {
            "Title": "Forest",
            "Link": "https://commons.wikimedia.org/wiki/Forest"
        },
        "eo": {
            "Title": "Arbaro",
            "Link": "https://eo.wikiquote.org/wiki/Arbaro"
        },
        "es": {
            "Title": "Bosque",
            "Link": "https://es.wikiquote.org/wiki/Bosque"
        },
        "et": {
            "Title": "Mets",
            "Link": "https://et.wikiquote.org/wiki/Mets"
        },
        "eu": {
            "Title": "Baso",
            "Link": "https://eu.wikipedia.org/wiki/Baso"
        },
        "fa": {
            "Title": "\u062c\u0646\u06af\u0644",
            "Link": "https://fa.wikipedia.org/wiki/%D8%AC%D9%86%DA%AF%D9%84"
        },
        "vro": {
            "Title": "M\u00f5ts",
            "Link": "https://fiu-vro.wikipedia.org/wiki/M%C3%B5ts"
        },
        "fi": {
            "Title": "Mets\u00e4",
            "Link": "https://fi.wikiquote.org/wiki/Mets%C3%A4"
        },
        "fj": {
            "Title": "Veikau",
            "Link": "https://fj.wikipedia.org/wiki/Veikau"
        },
        "fo": {
            "Title": "Sk\u00f3gur",
            "Link": "https://fo.wikipedia.org/wiki/Sk%C3%B3gur"
        },
        "frp": {
            "Title": "Jor",
            "Link": "https://frp.wikipedia.org/wiki/Jor"
        },
        "frr": {
            "Title": "Walt",
            "Link": "https://frr.wikipedia.org/wiki/Walt"
        },
        "fr": {
            "Title": "For\u00eat",
            "Link": "https://fr.wikiquote.org/wiki/For%C3%AAt"
        },
        "fy": {
            "Title": "W\u00e2ld",
            "Link": "https://fy.wikipedia.org/wiki/W%C3%A2ld"
        },
        "gan": {
            "Title": "\u68ee\u6797",
            "Link": "https://gan.wikipedia.org/wiki/%E6%A3%AE%E6%9E%97"
        },
        "ga": {
            "Title": "Foraois",
            "Link": "https://ga.wikipedia.org/wiki/Foraois"
        },
        "gcr": {
            "Title": "Danbwa",
            "Link": "https://gcr.wikipedia.org/wiki/Danbwa"
        },
        "gd": {
            "Title": "Coille",
            "Link": "https://gd.wikipedia.org/wiki/Coille"
        },
        "gl": {
            "Title": "Bosque",
            "Link": "https://gl.wikipedia.org/wiki/Bosque"
        },
        "gn": {
            "Title": "Ka'aguy",
            "Link": "https://gn.wikipedia.org/wiki/Ka%27aguy"
        },
        "ha": {
            "Title": "Gandun Daji",
            "Link": "https://ha.wikipedia.org/wiki/Gandun_Daji"
        },
        "he": {
            "Title": "\u05d9\u05e2\u05e8",
            "Link": "https://he.wikiquote.org/wiki/%D7%99%D7%A2%D7%A8"
        },
        "hif": {
            "Title": "Jangal",
            "Link": "https://hif.wikipedia.org/wiki/Jangal"
        },
        "hi": {
            "Title": "\u0935\u0928",
            "Link": "https://hi.wikipedia.org/wiki/%E0%A4%B5%E0%A4%A8"
        },
        "hr": {
            "Title": "\u0160uma",
            "Link": "https://hr.wikiquote.org/wiki/%C5%A0uma"
        },
        "ht": {
            "Title": "For\u00e8",
            "Link": "https://ht.wikipedia.org/wiki/For%C3%A8"
        },
        "hu": {
            "Title": "Erd\u0151",
            "Link": "https://hu.wikipedia.org/wiki/Erd%C5%91"
        },
        "hy": {
            "Title": "\u0531\u0576\u057f\u0561\u057c",
            "Link": "https://hy.wikiquote.org/wiki/%D4%B1%D5%B6%D5%BF%D5%A1%D5%BC"
        },
        "hyw": {
            "Title": "\u0531\u0576\u057f\u0561\u057c",
            "Link": "https://hyw.wikipedia.org/wiki/%D4%B1%D5%B6%D5%BF%D5%A1%D5%BC"
        },
        "ia": {
            "Title": "Foreste",
            "Link": "https://ia.wikipedia.org/wiki/Foreste"
        },
        "iba": {
            "Title": "Kampung",
            "Link": "https://iba.wikipedia.org/wiki/Kampung"
        },
        "id": {
            "Title": "Hutan",
            "Link": "https://id.wikipedia.org/wiki/Hutan"
        },
        "ik": {
            "Title": "Tiki\u0121aq (Napaaqtut)",
            "Link": "https://ik.wikipedia.org/wiki/Tiki%C4%A1aq_(Napaaqtut)"
        },
        "ilo": {
            "Title": "Bakir",
            "Link": "https://ilo.wikipedia.org/wiki/Bakir"
        },
        "inh": {
            "Title": "\u0425\u044c\u0443",
            "Link": "https://inh.wikipedia.org/wiki/%D0%A5%D1%8C%D1%83"
        },
        "io": {
            "Title": "Foresto",
            "Link": "https://io.wikipedia.org/wiki/Foresto"
        },
        "is": {
            "Title": "Sk\u00f3gur",
            "Link": "https://is.wikipedia.org/wiki/Sk%C3%B3gur"
        },
        "it": {
            "Title": "Foreste",
            "Link": "https://it.wikiversity.org/wiki/Foreste"
        },
        "jam": {
            "Title": "Faris",
            "Link": "https://jam.wikipedia.org/wiki/Faris"
        },
        "ja": {
            "Title": "\u68ee\u6797",
            "Link": "https://ja.wikipedia.org/wiki/%E6%A3%AE%E6%9E%97"
        },
        "jv": {
            "Title": "Alas",
            "Link": "https://jv.wikipedia.org/wiki/Alas"
        },
        "kab": {
            "Title": "Tagant",
            "Link": "https://kab.wikipedia.org/wiki/Tagant"
        },
        "ka": {
            "Title": "\u10e2\u10e7\u10d4",
            "Link": "https://ka.wikipedia.org/wiki/%E1%83%A2%E1%83%A7%E1%83%94"
        },
        "kbd": {
            "Title": "\u041c\u044d\u0437",
            "Link": "https://kbd.wikipedia.org/wiki/%D0%9C%D1%8D%D0%B7"
        },
        "kbp": {
            "Title": "La\u028b",
            "Link": "https://kbp.wikipedia.org/wiki/La%CA%8B"
        },
        "kcg": {
            "Title": "Sop",
            "Link": "https://kcg.wikipedia.org/wiki/Sop"
        },
        "kk": {
            "Title": "\u041e\u0440\u043c\u0430\u043d",
            "Link": "https://kk.wikipedia.org/wiki/%D0%9E%D1%80%D0%BC%D0%B0%D0%BD"
        },
        "kn": {
            "Title": "\u0c95\u0cbe\u0ca1\u0cc1",
            "Link": "https://kn.wikipedia.org/wiki/%E0%B2%95%E0%B2%BE%E0%B2%A1%E0%B3%81"
        },
        "ko": {
            "Title": "\uc232",
            "Link": "https://ko.wikiquote.org/wiki/%EC%88%B2"
        },
        "ks": {
            "Title": "\u0648\u064e\u0646",
            "Link": "https://ks.wikipedia.org/wiki/%D9%88%D9%8E%D9%86"
        },
        "ku": {
            "Title": "Daristan",
            "Link": "https://ku.wikiquote.org/wiki/Daristan"
        },
        "kv": {
            "Title": "\u0412\u04e7\u0440",
            "Link": "https://kv.wikipedia.org/wiki/%D0%92%D3%A7%D1%80"
        },
        "kw": {
            "Title": "Koswik",
            "Link": "https://kw.wikipedia.org/wiki/Koswik"
        },
        "ky": {
            "Title": "\u0422\u043e\u043a\u043e\u0439",
            "Link": "https://ky.wikipedia.org/wiki/%D0%A2%D0%BE%D0%BA%D0%BE%D0%B9"
        },
        "la": {
            "Title": "Silva",
            "Link": "https://la.wikiquote.org/wiki/Silva"
        },
        "lb": {
            "Title": "B\u00ebsch",
            "Link": "https://lb.wikipedia.org/wiki/B%C3%ABsch"
        },
        "lez": {
            "Title": "\u0422\u0430\u043c",
            "Link": "https://lez.wikipedia.org/wiki/%D0%A2%D0%B0%D0%BC"
        },
        "li": {
            "Title": "B\u00f3s",
            "Link": "https://li.wikipedia.org/wiki/B%C3%B3s"
        },
        "lmo": {
            "Title": "Foresta",
            "Link": "https://lmo.wikipedia.org/wiki/Foresta"
        },
        "ln": {
            "Title": "Z\u00e1mba",
            "Link": "https://ln.wikipedia.org/wiki/Z%C3%A1mba"
        },
        "lo": {
            "Title": "\u0e9b\u0ec8\u0eb2\u0ec4\u0ea1\u0ec9",
            "Link": "https://lo.wikipedia.org/wiki/%E0%BA%9B%E0%BB%88%E0%BA%B2%E0%BB%84%E0%BA%A1%E0%BB%89"
        },
        "lt": {
            "Title": "Mi\u0161kas",
            "Link": "https://lt.wikiquote.org/wiki/Mi%C5%A1kas"
        },
        "lv": {
            "Title": "Me\u017es",
            "Link": "https://lv.wikipedia.org/wiki/Me%C5%BEs"
        },
        "mg": {
            "Title": "Ala",
            "Link": "https://mg.wikipedia.org/wiki/Ala"
        },
        "min": {
            "Title": "Utan",
            "Link": "https://min.wikipedia.org/wiki/Utan"
        },
        "mk": {
            "Title": "\u0428\u0443\u043c\u0430",
            "Link": "https://mk.wikipedia.org/wiki/%D0%A8%D1%83%D0%BC%D0%B0"
        },
        "ml": {
            "Title": "\u0d35\u0d28\u0d02",
            "Link": "https://ml.wikipedia.org/wiki/%E0%B4%B5%E0%B4%A8%E0%B4%82"
        },
        "mni": {
            "Title": "\uabce\uabc3\uabea",
            "Link": "https://mni.wikipedia.org/wiki/%EA%AF%8E%EA%AF%83%EA%AF%AA"
        },
        "mrj": {
            "Title": "\u0428\u04f9\u0440\u0433\u04f9",
            "Link": "https://mrj.wikipedia.org/wiki/%D0%A8%D3%B9%D1%80%D0%B3%D3%B9"
        },
        "mr": {
            "Title": "\u0935\u0928",
            "Link": "https://mr.wikipedia.org/wiki/%E0%A4%B5%E0%A4%A8"
        },
        "ms": {
            "Title": "Hutan",
            "Link": "https://ms.wikipedia.org/wiki/Hutan"
        },
        "myv": {
            "Title": "\u0412\u0438\u0440\u044c",
            "Link": "https://myv.wikipedia.org/wiki/%D0%92%D0%B8%D1%80%D1%8C"
        },
        "my": {
            "Title": "\u101e\u1005\u103a\u1010\u1031\u102c",
            "Link": "https://my.wikipedia.org/wiki/%E1%80%9E%E1%80%85%E1%80%BA%E1%80%90%E1%80%B1%E1%80%AC"
        },
        "nah": {
            "Title": "Cuauhtlahtli",
            "Link": "https://nah.wikipedia.org/wiki/Cuauhtlahtli"
        },
        "nds-NL": {
            "Title": "Bos",
            "Link": "https://nds-nl.wikipedia.org/wiki/Bos"
        },
        "nds": {
            "Title": "Woold",
            "Link": "https://nds.wikipedia.org/wiki/Woold"
        },
        "ne": {
            "Title": "\u091c\u0919\u094d\u0917\u0932",
            "Link": "https://ne.wikipedia.org/wiki/%E0%A4%9C%E0%A4%99%E0%A5%8D%E0%A4%97%E0%A4%B2"
        },
        "new": {
            "Title": "\u0917\u0941\u0901",
            "Link": "https://new.wikipedia.org/wiki/%E0%A4%97%E0%A5%81%E0%A4%81"
        },
        "nl": {
            "Title": "Bos (vegetatie)",
            "Link": "https://nl.wikipedia.org/wiki/Bos_(vegetatie)"
        },
        "nn": {
            "Title": "Skog",
            "Link": "https://nn.wikiquote.org/wiki/Skog"
        },
        "no": {
            "Title": "Skog",
            "Link": "https://no.wikipedia.org/wiki/Skog"
        },
        "nrf": {
            "Title": "For\u00eat",
            "Link": "https://nrm.wikipedia.org/wiki/For%C3%AAt"
        },
        "nso": {
            "Title": "Sekgwa",
            "Link": "https://nso.wikipedia.org/wiki/Sekgwa"
        },
        "oc": {
            "Title": "For\u00e8st",
            "Link": "https://oc.wikipedia.org/wiki/For%C3%A8st"
        },
        "olo": {
            "Title": "Me\u010d\u010dy",
            "Link": "https://olo.wikipedia.org/wiki/Me%C4%8D%C4%8Dy"
        },
        "pam": {
            "Title": "Kakewan",
            "Link": "https://pam.wikipedia.org/wiki/Kakewan"
        },
        "pa": {
            "Title": "\u0a1c\u0a70\u0a17\u0a32",
            "Link": "https://pa.wikipedia.org/wiki/%E0%A8%9C%E0%A9%B0%E0%A8%97%E0%A8%B2"
        },
        "pi": {
            "Title": "\u0935\u0928\u0902",
            "Link": "https://pi.wikipedia.org/wiki/%E0%A4%B5%E0%A4%A8%E0%A4%82"
        },
        "pl": {
            "Title": "Las",
            "Link": "https://pl.wikiquote.org/wiki/Las"
        },
        "pnb": {
            "Title": "\u062c\u0646\u06af\u076a",
            "Link": "https://pnb.wikipedia.org/wiki/%D8%AC%D9%86%DA%AF%DD%AA"
        },
        "ps": {
            "Title": "\u0681\u0646\u06ab\u0644",
            "Link": "https://ps.wikipedia.org/wiki/%DA%81%D9%86%DA%AB%D9%84"
        },
        "pt": {
            "Title": "Floresta",
            "Link": "https://pt.wikiquote.org/wiki/Floresta"
        },
        "qu": {
            "Title": "Sach'a-sach'a",
            "Link": "https://qu.wikipedia.org/wiki/Sach%27a-sach%27a"
        },
        "rm": {
            "Title": "Guaud",
            "Link": "https://rm.wikipedia.org/wiki/Guaud"
        },
        "rmy": {
            "Title": "Vesh",
            "Link": "https://rmy.wikipedia.org/wiki/Vesh"
        },
        "rup": {
            "Title": "P\u00e2duri",
            "Link": "https://roa-rup.wikipedia.org/wiki/P%C3%A2duri"
        },
        "ro": {
            "Title": "P\u0103dure",
            "Link": "https://ro.wikipedia.org/wiki/P%C4%83dure"
        },
        "rue": {
            "Title": "\u041b\u0463\u0441",
            "Link": "https://rue.wikipedia.org/wiki/%D0%9B%D1%A3%D1%81"
        },
        "ru": {
            "Title": "\u041b\u0435\u0441",
            "Link": "https://ru.wikiquote.org/wiki/%D0%9B%D0%B5%D1%81"
        },
        "sah": {
            "Title": "\u0422\u044b\u0430",
            "Link": "https://sah.wikipedia.org/wiki/%D0%A2%D1%8B%D0%B0"
        },
        "sat": {
            "Title": "\u1c75\u1c64\u1c68",
            "Link": "https://sat.wikipedia.org/wiki/%E1%B1%B5%E1%B1%A4%E1%B1%A8"
        },
        "sa": {
            "Title": "\u0935\u0928\u092e\u094d",
            "Link": "https://sa.wikipedia.org/wiki/%E0%A4%B5%E0%A4%A8%E0%A4%AE%E0%A5%8D"
        },
        "scn": {
            "Title": "Guddefi",
            "Link": "https://scn.wikipedia.org/wiki/Guddefi"
        },
        "sco": {
            "Title": "Forest",
            "Link": "https://sco.wikipedia.org/wiki/Forest"
        },
        "sd": {
            "Title": "\u067b\u064a\u0644\u0648",
            "Link": "https://sd.wikipedia.org/wiki/%D9%BB%D9%8A%D9%84%D9%88"
        },
        "se": {
            "Title": "Vuovdi",
            "Link": "https://se.wikipedia.org/wiki/Vuovdi"
        },
        "shi": {
            "Title": "Tagant",
            "Link": "https://shi.wikipedia.org/wiki/Tagant"
        },
        "sh": {
            "Title": "\u0160uma",
            "Link": "https://sh.wikipedia.org/wiki/%C5%A0uma"
        },
        "en-simple": {
            "Title": "Forest",
            "Link": "https://simple.wikipedia.org/wiki/Forest"
        },
        "si": {
            "Title": "\u0dc0\u0db1\u0dcf\u0db1\u0dca\u0dad\u0dbb",
            "Link": "https://si.wikipedia.org/wiki/%E0%B7%80%E0%B6%B1%E0%B7%8F%E0%B6%B1%E0%B7%8A%E0%B6%AD%E0%B6%BB"
        },
        "sk": {
            "Title": "Les",
            "Link": "https://sk.wikiquote.org/wiki/Les"
        },
        "sl": {
            "Title": "Gozd",
            "Link": "https://sl.wikiquote.org/wiki/Gozd"
        },
        "sn": {
            "Title": "Sango",
            "Link": "https://sn.wikipedia.org/wiki/Sango"
        },
        "so": {
            "Title": "Keyn",
            "Link": "https://so.wikipedia.org/wiki/Keyn"
        },
        "sq": {
            "Title": "Pylli",
            "Link": "https://sq.wikipedia.org/wiki/Pylli"
        },
        "sr": {
            "Title": "\u0428\u0443\u043c\u0430",
            "Link": "https://sr.wikiquote.org/wiki/%D0%A8%D1%83%D0%BC%D0%B0"
        },
        "st": {
            "Title": "Morung",
            "Link": "https://st.wikipedia.org/wiki/Morung"
        },
        "su": {
            "Title": "Leuweung",
            "Link": "https://su.wikipedia.org/wiki/Leuweung"
        },
        "sv": {
            "Title": "Skog",
            "Link": "https://sv.wikipedia.org/wiki/Skog"
        },
        "sw": {
            "Title": "Msitu",
            "Link": "https://sw.wikipedia.org/wiki/Msitu"
        },
        "ta": {
            "Title": "\u0b95\u0bbe\u0b9f\u0bc1",
            "Link": "https://ta.wikipedia.org/wiki/%E0%AE%95%E0%AE%BE%E0%AE%9F%E0%AF%81"
        },
        "te": {
            "Title": "\u0c05\u0c21\u0c35\u0c3f",
            "Link": "https://te.wikipedia.org/wiki/%E0%B0%85%E0%B0%A1%E0%B0%B5%E0%B0%BF"
        },
        "tg": {
            "Title": "\u04b6\u0430\u043d\u0433\u0430\u043b",
            "Link": "https://tg.wikipedia.org/wiki/%D2%B6%D0%B0%D0%BD%D0%B3%D0%B0%D0%BB"
        },
        "th": {
            "Title": "\u0e1b\u0e48\u0e32",
            "Link": "https://th.wikipedia.org/wiki/%E0%B8%9B%E0%B9%88%E0%B8%B2"
        },
        "tk": {
            "Title": "Toka\u00fd",
            "Link": "https://tk.wikipedia.org/wiki/Toka%C3%BD"
        },
        "tl": {
            "Title": "Gubat",
            "Link": "https://tl.wikipedia.org/wiki/Gubat"
        },
        "tr": {
            "Title": "Orman",
            "Link": "https://tr.wikiquote.org/wiki/Orman"
        },
        "tt": {
            "Title": "\u0423\u0440\u043c\u0430\u043d",
            "Link": "https://tt.wikipedia.org/wiki/%D0%A3%D1%80%D0%BC%D0%B0%D0%BD"
        },
        "tw": {
            "Title": "Kwa\u025b",
            "Link": "https://tw.wikipedia.org/wiki/Kwa%C9%9B"
        },
        "ug": {
            "Title": "\u0626\u0648\u0631\u0645\u0627\u0646",
            "Link": "https://ug.wikipedia.org/wiki/%D8%A6%D9%88%D8%B1%D9%85%D8%A7%D9%86"
        },
        "uk": {
            "Title": "\u041b\u0456\u0441",
            "Link": "https://uk.wikiquote.org/wiki/%D0%9B%D1%96%D1%81"
        },
        "ur": {
            "Title": "\u062c\u0646\u06af\u0644",
            "Link": "https://ur.wikipedia.org/wiki/%D8%AC%D9%86%DA%AF%D9%84"
        },
        "uz": {
            "Title": "O\u02bbrmon",
            "Link": "https://uz.wikipedia.org/wiki/O%CA%BBrmon"
        },
        "vep": {
            "Title": "Mec",
            "Link": "https://vep.wikipedia.org/wiki/Mec"
        },
        "vi": {
            "Title": "R\u1eebng",
            "Link": "https://vi.wikipedia.org/wiki/R%E1%BB%ABng"
        },
        "vls": {
            "Title": "Bus",
            "Link": "https://vls.wikipedia.org/wiki/Bus"
        },
        "vo": {
            "Title": "Fot",
            "Link": "https://vo.wikipedia.org/wiki/Fot"
        },
        "war": {
            "Title": "Kagurangan",
            "Link": "https://war.wikipedia.org/wiki/Kagurangan"
        },
        "wa": {
            "Title": "Bw\u00e8s (d' \u00e5bes)",
            "Link": "https://wa.wikipedia.org/wiki/Bw%C3%A8s_(d%27_%C3%A5bes)"
        },
        "wuu": {
            "Title": "\u68ee\u6797",
            "Link": "https://wuu.wikipedia.org/wiki/%E6%A3%AE%E6%9E%97"
        },
        "xh": {
            "Title": "Ihlathi",
            "Link": "https://xh.wikipedia.org/wiki/Ihlathi"
        },
        "xmf": {
            "Title": "\u10e2\u10e7\u10d0",
            "Link": "https://xmf.wikipedia.org/wiki/%E1%83%A2%E1%83%A7%E1%83%90"
        },
        "yi": {
            "Title": "\u05d5\u05d5\u05d0\u05dc\u05d3",
            "Link": "https://yi.wikipedia.org/wiki/%D7%95%D7%95%D7%90%D7%9C%D7%93"
        },
        "za": {
            "Title": "Ndoengfaex",
            "Link": "https://za.wikipedia.org/wiki/Ndoengfaex"
        },
        "nan": {
            "Title": "Chhi\u016b-n\u00e2",
            "Link": "https://zh-min-nan.wikipedia.org/wiki/Chhi%C5%AB-n%C3%A2"
        },
        "yue": {
            "Title": "\u68ee\u6797",
            "Link": "https://zh-yue.wikipedia.org/wiki/%E6%A3%AE%E6%9E%97"
        },
        "zh": {
            "Title": "\u68ee\u6797",
            "Link": "https://zh.wikipedia.org/wiki/%E6%A3%AE%E6%9E%97"
        },
        "zu": {
            "Title": "Ihlathi",
            "Link": "https://zu.wikipedia.org/wiki/Ihlathi"
        }
    }
}