{
    "Q11990": {
        "af": {
            "Title": "Voortplanting",
            "Link": "https://af.wikipedia.org/wiki/Voortplanting"
        },
        "gsw": {
            "Title": "Fortpflanzung",
            "Link": "https://als.wikipedia.org/wiki/Fortpflanzung"
        },
        "an": {
            "Title": "Reproducci\u00f3n",
            "Link": "https://an.wikipedia.org/wiki/Reproducci%C3%B3n"
        },
        "ar": {
            "Title": "\u062a\u0643\u0627\u062b\u0631",
            "Link": "https://ar.wikipedia.org/wiki/%D8%AA%D9%83%D8%A7%D8%AB%D8%B1"
        },
        "arz": {
            "Title": "\u062a\u0643\u0627\u062b\u0631",
            "Link": "https://arz.wikipedia.org/wiki/%D8%AA%D9%83%D8%A7%D8%AB%D8%B1"
        },
        "ast": {
            "Title": "Reproducci\u00f3n",
            "Link": "https://ast.wikipedia.org/wiki/Reproducci%C3%B3n"
        },
        "as": {
            "Title": "\u09aa\u09cd\u09f0\u099c\u09a8\u09a8",
            "Link": "https://as.wikipedia.org/wiki/%E0%A6%AA%E0%A7%8D%E0%A7%B0%E0%A6%9C%E0%A6%A8%E0%A6%A8"
        },
        "azb": {
            "Title": "\u062a\u0624\u0631\u0647\u200c\u0645\u0647 (\u062a\u06a9\u062b\u06cc\u0631)",
            "Link": "https://azb.wikipedia.org/wiki/%D8%AA%D8%A4%D8%B1%D9%87%E2%80%8C%D9%85%D9%87_(%D8%AA%DA%A9%D8%AB%DB%8C%D8%B1)"
        },
        "az": {
            "Title": "N\u0259sil art\u0131rma",
            "Link": "https://az.wikipedia.org/wiki/N%C9%99sil_art%C4%B1rma"
        },
        "ba": {
            "Title": "\u04ae\u0440\u0441\u0435\u04af",
            "Link": "https://ba.wikipedia.org/wiki/%D2%AE%D1%80%D1%81%D0%B5%D2%AF"
        },
        "bcl": {
            "Title": "Reproduksyon",
            "Link": "https://bcl.wikipedia.org/wiki/Reproduksyon"
        },
        "be-tarask": {
            "Title": "\u0420\u0430\u0437\u043c\u043d\u0430\u0436\u044d\u043d\u044c\u043d\u0435",
            "Link": "https://be-tarask.wikipedia.org/wiki/%D0%A0%D0%B0%D0%B7%D0%BC%D0%BD%D0%B0%D0%B6%D1%8D%D0%BD%D1%8C%D0%BD%D0%B5"
        },
        "be": {
            "Title": "\u0420\u0430\u0437\u043c\u043d\u0430\u0436\u044d\u043d\u043d\u0435",
            "Link": "https://be.wikipedia.org/wiki/%D0%A0%D0%B0%D0%B7%D0%BC%D0%BD%D0%B0%D0%B6%D1%8D%D0%BD%D0%BD%D0%B5"
        },
        "bg": {
            "Title": "\u0420\u0430\u0437\u043c\u043d\u043e\u0436\u0430\u0432\u0430\u043d\u0435",
            "Link": "https://bg.wikipedia.org/wiki/%D0%A0%D0%B0%D0%B7%D0%BC%D0%BD%D0%BE%D0%B6%D0%B0%D0%B2%D0%B0%D0%BD%D0%B5"
        },
        "bn": {
            "Title": "\u09aa\u09cd\u09b0\u099c\u09a8\u09a8",
            "Link": "https://bn.wikipedia.org/wiki/%E0%A6%AA%E0%A7%8D%E0%A6%B0%E0%A6%9C%E0%A6%A8%E0%A6%A8"
        },
        "bs": {
            "Title": "Razmno\u017eavanje",
            "Link": "https://bs.wikipedia.org/wiki/Razmno%C5%BEavanje"
        },
        "ca": {
            "Title": "Reproducci\u00f3",
            "Link": "https://ca.wikipedia.org/wiki/Reproducci%C3%B3"
        },
        "ce": {
            "Title": "\u0414\u0435\u0431\u0430\u0440",
            "Link": "https://ce.wikipedia.org/wiki/%D0%94%D0%B5%D0%B1%D0%B0%D1%80"
        },
        "ckb": {
            "Title": "\u0632\u0627\u0648\u0632\u06ce",
            "Link": "https://ckb.wikipedia.org/wiki/%D8%B2%D8%A7%D9%88%D8%B2%DB%8E"
        },
        "cs": {
            "Title": "Rozmno\u017eov\u00e1n\u00ed",
            "Link": "https://cs.wikipedia.org/wiki/Rozmno%C5%BEov%C3%A1n%C3%AD"
        },
        "cy": {
            "Title": "Atgenhedlu",
            "Link": "https://cy.wikipedia.org/wiki/Atgenhedlu"
        },
        "da": {
            "Title": "Formering",
            "Link": "https://da.wikipedia.org/wiki/Formering"
        },
        "de": {
            "Title": "Fortpflanzung",
            "Link": "https://de.wikiquote.org/wiki/Fortpflanzung"
        },
        "el": {
            "Title": "\u0391\u03bd\u03b1\u03c0\u03b1\u03c1\u03b1\u03b3\u03c9\u03b3\u03ae",
            "Link": "https://el.wikipedia.org/wiki/%CE%91%CE%BD%CE%B1%CF%80%CE%B1%CF%81%CE%B1%CE%B3%CF%89%CE%B3%CE%AE"
        },
        "en": {
            "Title": "Reproduction",
            "Link": "https://en.wikipedia.org/wiki/Reproduction"
        },
        "eo": {
            "Title": "Reproduktado",
            "Link": "https://eo.wikipedia.org/wiki/Reproduktado"
        },
        "es": {
            "Title": "Reproducci\u00f3n",
            "Link": "https://es.wikipedia.org/wiki/Reproducci%C3%B3n"
        },
        "et": {
            "Title": "Paljunemine",
            "Link": "https://et.wikiquote.org/wiki/Paljunemine"
        },
        "eu": {
            "Title": "Ugalketa",
            "Link": "https://eu.wikipedia.org/wiki/Ugalketa"
        },
        "ext": {
            "Title": "Reproducion",
            "Link": "https://ext.wikipedia.org/wiki/Reproducion"
        },
        "fa": {
            "Title": "\u062a\u0648\u0644\u06cc\u062f\u0645\u062b\u0644",
            "Link": "https://fa.wikipedia.org/wiki/%D8%AA%D9%88%D9%84%DB%8C%D8%AF%D9%85%D8%AB%D9%84"
        },
        "fi": {
            "Title": "Lis\u00e4\u00e4ntyminen",
            "Link": "https://fi.wikipedia.org/wiki/Lis%C3%A4%C3%A4ntyminen"
        },
        "fr": {
            "Title": "Reproduction des organismes animaux et v\u00e9g\u00e9taux",
            "Link": "https://fr.wikiversity.org/wiki/Reproduction_des_organismes_animaux_et_v%C3%A9g%C3%A9taux"
        },
        "fy": {
            "Title": "Fuortplanting",
            "Link": "https://fy.wikipedia.org/wiki/Fuortplanting"
        },
        "ga": {
            "Title": "At\u00e1irgeadh",
            "Link": "https://ga.wikipedia.org/wiki/At%C3%A1irgeadh"
        },
        "gcr": {
            "Title": "Rouprodiksyon (byoloji)",
            "Link": "https://gcr.wikipedia.org/wiki/Rouprodiksyon_(byoloji)"
        },
        "gl": {
            "Title": "Reproduci\u00f3n",
            "Link": "https://gl.wikipedia.org/wiki/Reproduci%C3%B3n"
        },
        "gn": {
            "Title": "\u00d1emo\u00f1a",
            "Link": "https://gn.wikipedia.org/wiki/%C3%91emo%C3%B1a"
        },
        "he": {
            "Title": "\u05e8\u05d1\u05d9\u05d9\u05d4",
            "Link": "https://he.wikiquote.org/wiki/%D7%A8%D7%91%D7%99%D7%99%D7%94"
        },
        "hif": {
            "Title": "Reproduction",
            "Link": "https://hif.wikipedia.org/wiki/Reproduction"
        },
        "hi": {
            "Title": "\u091c\u0928\u0928",
            "Link": "https://hi.wikipedia.org/wiki/%E0%A4%9C%E0%A4%A8%E0%A4%A8"
        },
        "hr": {
            "Title": "Reprodukcija",
            "Link": "https://hr.wikipedia.org/wiki/Reprodukcija"
        },
        "ht": {
            "Title": "Repwodiksyon",
            "Link": "https://ht.wikipedia.org/wiki/Repwodiksyon"
        },
        "hu": {
            "Title": "Szaporod\u00e1s",
            "Link": "https://hu.wikipedia.org/wiki/Szaporod%C3%A1s"
        },
        "hy": {
            "Title": "\u0532\u0561\u0566\u0574\u0561\u0581\u0578\u0582\u0574",
            "Link": "https://hy.wikipedia.org/wiki/%D4%B2%D5%A1%D5%A6%D5%B4%D5%A1%D6%81%D5%B8%D6%82%D5%B4"
        },
        "hyw": {
            "Title": "\u0532\u0561\u0566\u0574\u0561\u0581\u0578\u0582\u0574",
            "Link": "https://hyw.wikipedia.org/wiki/%D4%B2%D5%A1%D5%A6%D5%B4%D5%A1%D6%81%D5%B8%D6%82%D5%B4"
        },
        "id": {
            "Title": "Reproduksi",
            "Link": "https://id.wikipedia.org/wiki/Reproduksi"
        },
        "ilo": {
            "Title": "Reproduksion",
            "Link": "https://ilo.wikipedia.org/wiki/Reproduksion"
        },
        "inh": {
            "Title": "\u0414\u0435\u0431\u0430\u0434\u0430\u043b\u0430\u0440",
            "Link": "https://inh.wikipedia.org/wiki/%D0%94%D0%B5%D0%B1%D0%B0%D0%B4%D0%B0%D0%BB%D0%B0%D1%80"
        },
        "io": {
            "Title": "Genitado",
            "Link": "https://io.wikipedia.org/wiki/Genitado"
        },
        "is": {
            "Title": "\u00c6xlun",
            "Link": "https://is.wikipedia.org/wiki/%C3%86xlun"
        },
        "it": {
            "Title": "Riproduzione",
            "Link": "https://it.wikiquote.org/wiki/Riproduzione"
        },
        "jam": {
            "Title": "Riprodokshan",
            "Link": "https://jam.wikipedia.org/wiki/Riprodokshan"
        },
        "ja": {
            "Title": "\u751f\u6b96",
            "Link": "https://ja.wikipedia.org/wiki/%E7%94%9F%E6%AE%96"
        },
        "jv": {
            "Title": "R\u00e9prodhuksi",
            "Link": "https://jv.wikipedia.org/wiki/R%C3%A9prodhuksi"
        },
        "kab": {
            "Title": "Talsuff\u0263a",
            "Link": "https://kab.wikipedia.org/wiki/Talsuff%C9%A3a"
        },
        "ka": {
            "Title": "\u10d2\u10d0\u10db\u10e0\u10d0\u10d5\u10da\u10d4\u10d1\u10d0",
            "Link": "https://ka.wikipedia.org/wiki/%E1%83%92%E1%83%90%E1%83%9B%E1%83%A0%E1%83%90%E1%83%95%E1%83%9A%E1%83%94%E1%83%91%E1%83%90"
        },
        "ki": {
            "Title": "Njiarano(reproduction)",
            "Link": "https://ki.wikipedia.org/wiki/Njiarano(reproduction)"
        },
        "kk": {
            "Title": "\u041a\u04e9\u0431\u0435\u044e",
            "Link": "https://kk.wikipedia.org/wiki/%D0%9A%D3%A9%D0%B1%D0%B5%D1%8E"
        },
        "kn": {
            "Title": "\u0caa\u0ccd\u0cb0\u0c9c\u0ca8\u0ca8",
            "Link": "https://kn.wikipedia.org/wiki/%E0%B2%AA%E0%B3%8D%E0%B2%B0%E0%B2%9C%E0%B2%A8%E0%B2%A8"
        },
        "ko": {
            "Title": "\uc0dd\uc2dd",
            "Link": "https://ko.wikipedia.org/wiki/%EC%83%9D%EC%8B%9D"
        },
        "krc": {
            "Title": "\u041a\u0451\u0431\u043b\u0435\u043d\u0438\u0443",
            "Link": "https://krc.wikipedia.org/wiki/%D0%9A%D1%91%D0%B1%D0%BB%D0%B5%D0%BD%D0%B8%D1%83"
        },
        "kw": {
            "Title": "Dinythians",
            "Link": "https://kw.wikipedia.org/wiki/Dinythians"
        },
        "ky": {
            "Title": "\u041a\u04e9\u0431\u04e9\u0439\u04af\u04af",
            "Link": "https://ky.wikipedia.org/wiki/%D0%9A%D3%A9%D0%B1%D3%A9%D0%B9%D2%AF%D2%AF"
        },
        "la": {
            "Title": "Procreatio",
            "Link": "https://la.wikipedia.org/wiki/Procreatio"
        },
        "li": {
            "Title": "Veurtplantjing",
            "Link": "https://li.wikipedia.org/wiki/Veurtplantjing"
        },
        "lmo": {
            "Title": "Reproduzion",
            "Link": "https://lmo.wikipedia.org/wiki/Reproduzion"
        },
        "lt": {
            "Title": "Dauginimasis",
            "Link": "https://lt.wikipedia.org/wiki/Dauginimasis"
        },
        "lv": {
            "Title": "Vairo\u0161an\u0101s",
            "Link": "https://lv.wikipedia.org/wiki/Vairo%C5%A1an%C4%81s"
        },
        "mhr": {
            "Title": "\u0422\u04f1\u043b\u044b\u043c\u0430\u0448",
            "Link": "https://mhr.wikipedia.org/wiki/%D0%A2%D3%B1%D0%BB%D1%8B%D0%BC%D0%B0%D1%88"
        },
        "mk": {
            "Title": "\u0420\u0430\u0437\u043c\u043d\u043e\u0436\u0443\u0432\u0430\u045a\u0435",
            "Link": "https://mk.wikipedia.org/wiki/%D0%A0%D0%B0%D0%B7%D0%BC%D0%BD%D0%BE%D0%B6%D1%83%D0%B2%D0%B0%D1%9A%D0%B5"
        },
        "ml": {
            "Title": "\u0d2a\u0d4d\u0d30\u0d24\u0d4d\u0d2f\u0d41\u0d7d\u0d2a\u0d4d\u0d2a\u0d3e\u0d26\u0d28\u0d02",
            "Link": "https://ml.wikipedia.org/wiki/%E0%B4%AA%E0%B5%8D%E0%B4%B0%E0%B4%A4%E0%B5%8D%E0%B4%AF%E0%B5%81%E0%B5%BD%E0%B4%AA%E0%B5%8D%E0%B4%AA%E0%B4%BE%E0%B4%A6%E0%B4%A8%E0%B4%82"
        },
        "mr": {
            "Title": "\u092a\u094d\u0930\u091c\u0928\u0928",
            "Link": "https://mr.wikipedia.org/wiki/%E0%A4%AA%E0%A5%8D%E0%A4%B0%E0%A4%9C%E0%A4%A8%E0%A4%A8"
        },
        "ms": {
            "Title": "Pembiakan",
            "Link": "https://ms.wikipedia.org/wiki/Pembiakan"
        },
        "my": {
            "Title": "\u1019\u103b\u102d\u102f\u1038\u1015\u103d\u102c\u1038\u1001\u103c\u1004\u103a\u1038",
            "Link": "https://my.wikipedia.org/wiki/%E1%80%99%E1%80%BB%E1%80%AD%E1%80%AF%E1%80%B8%E1%80%95%E1%80%BD%E1%80%AC%E1%80%B8%E1%80%81%E1%80%BC%E1%80%84%E1%80%BA%E1%80%B8"
        },
        "nds": {
            "Title": "Reproduktschoon",
            "Link": "https://nds.wikipedia.org/wiki/Reproduktschoon"
        },
        "ne": {
            "Title": "\u092a\u094d\u0930\u091c\u0928\u0928 (\u092a\u0941\u0928\u0930\u0941\u0924\u094d\u092a\u093e\u0926\u0928)",
            "Link": "https://ne.wikipedia.org/wiki/%E0%A4%AA%E0%A5%8D%E0%A4%B0%E0%A4%9C%E0%A4%A8%E0%A4%A8_(%E0%A4%AA%E0%A5%81%E0%A4%A8%E0%A4%B0%E0%A5%81%E0%A4%A4%E0%A5%8D%E0%A4%AA%E0%A4%BE%E0%A4%A6%E0%A4%A8)"
        },
        "new": {
            "Title": "\u092e\u091a\u093e \u092c\u0941\u0907\u0915\u093f\u0917\u0941",
            "Link": "https://new.wikipedia.org/wiki/%E0%A4%AE%E0%A4%9A%E0%A4%BE_%E0%A4%AC%E0%A5%81%E0%A4%87%E0%A4%95%E0%A4%BF%E0%A4%97%E0%A5%81"
        },
        "nl": {
            "Title": "Voortplanting (biologie)",
            "Link": "https://nl.wikipedia.org/wiki/Voortplanting_(biologie)"
        },
        "nn": {
            "Title": "Forplanting",
            "Link": "https://nn.wikipedia.org/wiki/Forplanting"
        },
        "no": {
            "Title": "Formering",
            "Link": "https://no.wikipedia.org/wiki/Formering"
        },
        "oc": {
            "Title": "Reproduccion",
            "Link": "https://oc.wikipedia.org/wiki/Reproduccion"
        },
        "pam": {
            "Title": "Pamiparakal",
            "Link": "https://pam.wikipedia.org/wiki/Pamiparakal"
        },
        "pa": {
            "Title": "\u0a2a\u0a4d\u0a30\u0a1c\u0a28\u0a28",
            "Link": "https://pa.wikipedia.org/wiki/%E0%A8%AA%E0%A9%8D%E0%A8%B0%E0%A8%9C%E0%A8%A8%E0%A8%A8"
        },
        "pl": {
            "Title": "Rozmna\u017canie",
            "Link": "https://pl.wikipedia.org/wiki/Rozmna%C5%BCanie"
        },
        "pnb": {
            "Title": "\u062c\u0645\u0646",
            "Link": "https://pnb.wikipedia.org/wiki/%D8%AC%D9%85%D9%86"
        },
        "ps": {
            "Title": "\u0628\u064a\u0627 \u062a\u0648\u0644\u064a\u062f (\u062f \u062e\u067e\u0644 \u0645\u062b\u0644 \u0632\u06d0\u0696\u0648\u0644)",
            "Link": "https://ps.wikipedia.org/wiki/%D8%A8%D9%8A%D8%A7_%D8%AA%D9%88%D9%84%D9%8A%D8%AF_(%D8%AF_%D8%AE%D9%BE%D9%84_%D9%85%D8%AB%D9%84_%D8%B2%DB%90%DA%96%D9%88%D9%84)"
        },
        "pt": {
            "Title": "Reprodu\u00e7\u00e3o",
            "Link": "https://pt.wikipedia.org/wiki/Reprodu%C3%A7%C3%A3o"
        },
        "qu": {
            "Title": "Miraykuy",
            "Link": "https://qu.wikipedia.org/wiki/Miraykuy"
        },
        "ro": {
            "Title": "Reproducere",
            "Link": "https://ro.wikipedia.org/wiki/Reproducere"
        },
        "rue": {
            "Title": "\u0420\u043e\u0437\u043c\u043d\u043e\u0436\u043e\u0432\u0430\u043d\u044f",
            "Link": "https://rue.wikipedia.org/wiki/%D0%A0%D0%BE%D0%B7%D0%BC%D0%BD%D0%BE%D0%B6%D0%BE%D0%B2%D0%B0%D0%BD%D1%8F"
        },
        "ru": {
            "Title": "\u041a\u0430\u0442\u0435\u0433\u043e\u0440\u0438\u044f:\u0420\u0430\u0437\u043c\u043d\u043e\u0436\u0435\u043d\u0438\u0435",
            "Link": "https://ru.wikinews.org/wiki/%D0%9A%D0%B0%D1%82%D0%B5%D0%B3%D0%BE%D1%80%D0%B8%D1%8F:%D0%A0%D0%B0%D0%B7%D0%BC%D0%BD%D0%BE%D0%B6%D0%B5%D0%BD%D0%B8%D0%B5"
        },
        "sah": {
            "Title": "\u0423\u0443\u04bb\u0430\u0430\u04bb\u044b\u043d",
            "Link": "https://sah.wikipedia.org/wiki/%D0%A3%D1%83%D2%BB%D0%B0%D0%B0%D2%BB%D1%8B%D0%BD"
        },
        "sd": {
            "Title": "\u067e\u064a\u062f\u0627\u0626\u0634\u064a \u0639\u0645\u0644",
            "Link": "https://sd.wikipedia.org/wiki/%D9%BE%D9%8A%D8%AF%D8%A7%D8%A6%D8%B4%D9%8A_%D8%B9%D9%85%D9%84"
        },
        "sh": {
            "Title": "Razmno\u017eavanje",
            "Link": "https://sh.wikipedia.org/wiki/Razmno%C5%BEavanje"
        },
        "en-simple": {
            "Title": "Reproduction",
            "Link": "https://simple.wikipedia.org/wiki/Reproduction"
        },
        "si": {
            "Title": "\u0db4\u0dca\u200d\u0dbb\u0da2\u0db1\u0db1\u0dba",
            "Link": "https://si.wikipedia.org/wiki/%E0%B6%B4%E0%B7%8A%E2%80%8D%E0%B6%BB%E0%B6%A2%E0%B6%B1%E0%B6%B1%E0%B6%BA"
        },
        "sk": {
            "Title": "Reprodukcia",
            "Link": "https://sk.wikiquote.org/wiki/Reprodukcia"
        },
        "sl": {
            "Title": "Razmno\u017eevanje",
            "Link": "https://sl.wikipedia.org/wiki/Razmno%C5%BEevanje"
        },
        "sn": {
            "Title": "Sikarudzi",
            "Link": "https://sn.wikipedia.org/wiki/Sikarudzi"
        },
        "sq": {
            "Title": "Riprodhimi",
            "Link": "https://sq.wikipedia.org/wiki/Riprodhimi"
        },
        "sr": {
            "Title": "\u0420\u0435\u043f\u0440\u043e\u0434\u0443\u043a\u0446\u0438\u0458\u0430",
            "Link": "https://sr.wikipedia.org/wiki/%D0%A0%D0%B5%D0%BF%D1%80%D0%BE%D0%B4%D1%83%D0%BA%D1%86%D0%B8%D1%98%D0%B0"
        },
        "su": {
            "Title": "Baranahan",
            "Link": "https://su.wikipedia.org/wiki/Baranahan"
        },
        "sv": {
            "Title": "Fortplantning",
            "Link": "https://sv.wikipedia.org/wiki/Fortplantning"
        },
        "sw": {
            "Title": "Uzazi",
            "Link": "https://sw.wikipedia.org/wiki/Uzazi"
        },
        "ta": {
            "Title": "\u0b87\u0ba9\u0baa\u0bcd\u0baa\u0bc6\u0bb0\u0bc1\u0b95\u0bcd\u0b95\u0bae\u0bcd",
            "Link": "https://ta.wikipedia.org/wiki/%E0%AE%87%E0%AE%A9%E0%AE%AA%E0%AF%8D%E0%AE%AA%E0%AF%86%E0%AE%B0%E0%AF%81%E0%AE%95%E0%AF%8D%E0%AE%95%E0%AE%AE%E0%AF%8D"
        },
        "tay": {
            "Title": "kinbhoyaw",
            "Link": "https://tay.wikipedia.org/wiki/kinbhoyaw"
        },
        "te": {
            "Title": "\u0c2a\u0c41\u0c28\u0c30\u0c41\u0c24\u0c4d\u0c2a\u0c24\u0c4d\u0c24\u0c3f",
            "Link": "https://te.wikipedia.org/wiki/%E0%B0%AA%E0%B1%81%E0%B0%A8%E0%B0%B0%E0%B1%81%E0%B0%A4%E0%B1%8D%E0%B0%AA%E0%B0%A4%E0%B1%8D%E0%B0%A4%E0%B0%BF"
        },
        "tg": {
            "Title": "\u0417\u043e\u0434\u043e\u0432\u0430\u0440\u04e3",
            "Link": "https://tg.wikipedia.org/wiki/%D0%97%D0%BE%D0%B4%D0%BE%D0%B2%D0%B0%D1%80%D3%A3"
        },
        "th": {
            "Title": "\u0e01\u0e32\u0e23\u0e2a\u0e37\u0e1a\u0e1e\u0e31\u0e19\u0e18\u0e38\u0e4c",
            "Link": "https://th.wikipedia.org/wiki/%E0%B8%81%E0%B8%B2%E0%B8%A3%E0%B8%AA%E0%B8%B7%E0%B8%9A%E0%B8%9E%E0%B8%B1%E0%B8%99%E0%B8%98%E0%B8%B8%E0%B9%8C"
        },
        "tl": {
            "Title": "Pagpaparami",
            "Link": "https://tl.wikipedia.org/wiki/Pagpaparami"
        },
        "tr": {
            "Title": "\u00dcreme",
            "Link": "https://tr.wikipedia.org/wiki/%C3%9Creme"
        },
        "tt": {
            "Title": "\u04ae\u0440\u0447\u04af",
            "Link": "https://tt.wikipedia.org/wiki/%D2%AE%D1%80%D1%87%D2%AF"
        },
        "uk": {
            "Title": "\u0420\u043e\u0437\u043c\u043d\u043e\u0436\u0435\u043d\u043d\u044f",
            "Link": "https://uk.wikipedia.org/wiki/%D0%A0%D0%BE%D0%B7%D0%BC%D0%BD%D0%BE%D0%B6%D0%B5%D0%BD%D0%BD%D1%8F"
        },
        "ur": {
            "Title": "\u062a\u0648\u0644\u06cc\u062f",
            "Link": "https://ur.wikipedia.org/wiki/%D8%AA%D9%88%D9%84%DB%8C%D8%AF"
        },
        "uz": {
            "Title": "Ko\u02bbpayish",
            "Link": "https://uz.wikipedia.org/wiki/Ko%CA%BBpayish"
        },
        "vec": {
            "Title": "Reprodusion",
            "Link": "https://vec.wikipedia.org/wiki/Reprodusion"
        },
        "vi": {
            "Title": "Sinh s\u1ea3n",
            "Link": "https://vi.wikipedia.org/wiki/Sinh_s%E1%BA%A3n"
        },
        "war": {
            "Title": "Reproduksyon",
            "Link": "https://war.wikipedia.org/wiki/Reproduksyon"
        },
        "wa": {
            "Title": "Mopliyaedje (biyolodjeye)",
            "Link": "https://wa.wikipedia.org/wiki/Mopliyaedje_(biyolodjeye)"
        },
        "wuu": {
            "Title": "\u7e41\u6b96",
            "Link": "https://wuu.wikipedia.org/wiki/%E7%B9%81%E6%AE%96"
        },
        "xmf": {
            "Title": "\u10eb\u10d8\u10dc\u10d0",
            "Link": "https://xmf.wikipedia.org/wiki/%E1%83%AB%E1%83%98%E1%83%9C%E1%83%90"
        },
        "yi": {
            "Title": "\u05e8\u05e2\u05e4\u05e8\u05d0\u05d3\u05d5\u05e7\u05e6\u05d9\u05e2",
            "Link": "https://yi.wikipedia.org/wiki/%D7%A8%D7%A2%D7%A4%D7%A8%D7%90%D7%93%D7%95%D7%A7%D7%A6%D7%99%D7%A2"
        },
        "nan": {
            "Title": "Se\u207f-tho\u00e0\u207f",
            "Link": "https://zh-min-nan.wikipedia.org/wiki/Se%E2%81%BF-tho%C3%A0%E2%81%BF"
        },
        "yue": {
            "Title": "\u751f\u6b96",
            "Link": "https://zh-yue.wikipedia.org/wiki/%E7%94%9F%E6%AE%96"
        },
        "zh": {
            "Title": "\u7e41\u6b96",
            "Link": "https://zh.wikipedia.org/wiki/%E7%B9%81%E6%AE%96"
        }
    }
}